Workbook

Sheet Summary Dashboard
A1: Tekton Platform & Agentic Builder - QA Test Suite
A2: Interactive Manual QA Dashboard — Live Dynamic Formulas Linked Across All Page Sheets
A4: TOTAL TEST CASES | C4: PASSED | D4: FAILED | E4: UNKNOWN / UNTESTED | G4: OVERALL % SUCCESS
A5: =C26 -> 180 | C5: =D26 -> 0 | D5: =E26 -> 0 | E5: =F26 -> 180 | G5: =IF((D26+E26)>0, D26/(D26+E26), 0) -> 0
A7: Test Execution Breakdown by Page & Feature (Formulas Connected to Page Sheets)
A8: Feature / Page Area | B8: Target Route | C8: Total Test Cases | D8: Passed | E8: Failed | F8: Unknown / Untested | G8: % Success (Pass Rate) | H8: Primary Scope / Capabilities Verified
A9: Agentic Builder | B9: #/new | C9: =COUNTIF('Agentic Builder'!G2:G21, "<>") -> 20 | D9: =COUNTIF('Agentic Builder'!G2:G21, "Pass") -> 0 | E9: =COUNTIF('Agentic Builder'!G2:G21, "Fail") -> 0 | F9: =COUNTIF('Agentic Builder'!G2:G21, "Unknown") -> 20 | G9: =IF((D9+E9)>0, D9/(D9+E9), 0) -> 0 | H9: Natural language editing, URL crawl, PDF/OCR vision extraction, conflict reconciliation, grounding, undo
A10: Home | B10: #/ | C10: =COUNTIF(Home!G2:G11, "<>") -> 10 | D10: =COUNTIF(Home!G2:G11, "Pass") -> 0 | E10: =COUNTIF(Home!G2:G11, "Fail") -> 0 | F10: =COUNTIF(Home!G2:G11, "Unknown") -> 10 | G10: =IF((D10+E10)>0, D10/(D10+E10), 0) -> 0 | H10: Hero CTAs, feature navigation, giving progress bar, ministries list, recent sermons, contact block
A11: Plan Your Visit | B11: #/guests/plan | C11: =COUNTIF('Plan Your Visit'!G2:G11, "<>") -> 10 | D11: =COUNTIF('Plan Your Visit'!G2:G11, "Pass") -> 0 | E11: =COUNTIF('Plan Your Visit'!G2:G11, "Fail") -> 0 | F11: =COUNTIF('Plan Your Visit'!G2:G11, "Unknown") -> 10 | G11: =IF((D11+E11)>0, D11/(D11+E11), 0) -> 0 | H11: RSVP form submission, validation, campus parking map selection, arrival flow, FAQ accordion
A12: Welcome Team | B12: #/guests/welcome | C12: =COUNTIF('Welcome Team'!G2:G11, "<>") -> 10 | D12: =COUNTIF('Welcome Team'!G2:G11, "Pass") -> 0 | E12: =COUNTIF('Welcome Team'!G2:G11, "Fail") -> 0 | F12: =COUNTIF('Welcome Team'!G2:G11, "Unknown") -> 10 | G12: =IF((D12+E12)>0, D12/(D12+E12), 0) -> 0 | H12: Staff-only arrival queue, host claiming, notifications, arrival time metrics, live polling
A13: Serve | B13: #/serve | C13: =COUNTIF(Serve!G2:G11, "<>") -> 10 | D13: =COUNTIF(Serve!G2:G11, "Pass") -> 0 | E13: =COUNTIF(Serve!G2:G11, "Fail") -> 0 | F13: =COUNTIF(Serve!G2:G11, "Unknown") -> 10 | G13: =IF((D13+E13)>0, D13/(D13+E13), 0) -> 0 | H13: Keyword search, urgent needs filter, AI matching recommendations, bookmarking, staff request queue
A14: Sermon Notes | B14: #/notes | C14: =COUNTIF('Sermon Notes'!G2:G11, "<>") -> 10 | D14: =COUNTIF('Sermon Notes'!G2:G11, "Pass") -> 0 | E14: =COUNTIF('Sermon Notes'!G2:G11, "Fail") -> 0 | F14: =COUNTIF('Sermon Notes'!G2:G11, "Unknown") -> 10 | G14: =IF((D14+E14)>0, D14/(D14+E14), 0) -> 0 | H14: Transcript browsing, AI sermon Q&A with timestamps, media playback sync, YouVersion verse lookup, upload
A15: Calendar | B15: #/calendar | C15: =COUNTIF(Calendar!G2:G11, "<>") -> 10 | D15: =COUNTIF(Calendar!G2:G11, "Pass") -> 0 | E15: =COUNTIF(Calendar!G2:G11, "Fail") -> 0 | F15: =COUNTIF(Calendar!G2:G11, "Unknown") -> 10 | G15: =IF((D15+E15)>0, D15/(D15+E15), 0) -> 0 | H15: Monthly grid & list views, category filter, keyword search, month navigation, staff event CRUD
A16: Give | B16: #/give | C16: =COUNTIF(Give!G2:G11, "<>") -> 10 | D16: =COUNTIF(Give!G2:G11, "Pass") -> 0 | E16: =COUNTIF(Give!G2:G11, "Fail") -> 0 | F16: =COUNTIF(Give!G2:G11, "Unknown") -> 10 | G16: =IF((D16+E16)>0, D16/(D16+E16), 0) -> 0 | H16: Donation presets, custom amounts, fund selector, recurring monthly toggle, Stripe checkout, trips
A17: Prayer Map | B17: #/prayer | C17: =COUNTIF('Prayer Map'!G2:G11, "<>") -> 10 | D17: =COUNTIF('Prayer Map'!G2:G11, "Pass") -> 0 | E17: =COUNTIF('Prayer Map'!G2:G11, "Fail") -> 0 | F17: =COUNTIF('Prayer Map'!G2:G11, "Unknown") -> 10 | G17: =IF((D17+E17)>0, D17/(D17+E17), 0) -> 0 | H17: Leaflet world map, country prayer beacons, verified news pins, sensitive country anonymization
A18: About - Our Story | B18: #/about | C18: =COUNTIF('About - Our Story'!G2:G11, "<>") -> 10 | D18: =COUNTIF('About - Our Story'!G2:G11, "Pass") -> 0 | E18: =COUNTIF('About - Our Story'!G2:G11, "Fail") -> 0 | F18: =COUNTIF('About - Our Story'!G2:G11, "Unknown") -> 10 | G18: =IF((D18+E18)>0, D18/(D18+E18), 0) -> 0 | H18: Mission statement, narrative story, core value cards, visit block, provenance quote inspect
A19: About - Beliefs | B19: #/about/beliefs | C19: =COUNTIF('About - Beliefs'!G2:G11, "<>") -> 10 | D19: =COUNTIF('About - Beliefs'!G2:G11, "Pass") -> 0 | E19: =COUNTIF('About - Beliefs'!G2:G11, "Fail") -> 0 | F19: =COUNTIF('About - Beliefs'!G2:G11, "Unknown") -> 10 | G19: =IF((D19+E19)>0, D19/(D19+E19), 0) -> 0 | H19: Doctrinal preamble, numbered belief articles, custom imported beliefs, sub-navigation
A20: About - News | B20: #/about/news | C20: =COUNTIF('About - News'!G2:G11, "<>") -> 10 | D20: =COUNTIF('About - News'!G2:G11, "Pass") -> 0 | E20: =COUNTIF('About - News'!G2:G11, "Fail") -> 0 | F20: =COUNTIF('About - News'!G2:G11, "Unknown") -> 10 | G20: =IF((D20+E20)>0, D20/(D20+E20), 0) -> 0 | H20: Updates vs articles filter, taxonomy tags, AI 3-bullet summary, staff post publishing & moderation
A21: About - Directory | B21: #/about/directory | C21: =COUNTIF('About - Directory'!G2:G11, "<>") -> 10 | D21: =COUNTIF('About - Directory'!G2:G11, "Pass") -> 0 | E21: =COUNTIF('About - Directory'!G2:G11, "Fail") -> 0 | F21: =COUNTIF('About - Directory'!G2:G11, "Unknown") -> 10 | G21: =IF((D21+E21)>0, D21/(D21+E21), 0) -> 0 | H21: Staff search, role filtering, click-to-call, click-to-email, office hours, ministry leaders
A22: About - Connect | B22: #/about/connect | C22: =COUNTIF('About - Connect'!G2:G11, "<>") -> 10 | D22: =COUNTIF('About - Connect'!G2:G11, "Pass") -> 0 | E22: =COUNTIF('About - Connect'!G2:G11, "Fail") -> 0 | F22: =COUNTIF('About - Connect'!G2:G11, "Unknown") -> 10 | G22: =IF((D22+E22)>0, D22/(D22+E22), 0) -> 0 | H22: Next step pathways, small groups directory, imported external forms, email inquiry mailto generator
A23: Admin - Staff | B23: #/staff | C23: =COUNTIF('Admin - Staff'!G2:G11, "<>") -> 10 | D23: =COUNTIF('Admin - Staff'!G2:G11, "Pass") -> 0 | E23: =COUNTIF('Admin - Staff'!G2:G11, "Fail") -> 0 | F23: =COUNTIF('Admin - Staff'!G2:G11, "Unknown") -> 10 | G23: =IF((D23+E23)>0, D23/(D23+E23), 0) -> 0 | H23: Staff sign-in, Stripe onboarding, funds management, trip applications review, donor gifts ledger
A24: Admin - Setup | B24: #/setup | C24: =COUNTIF('Admin - Setup'!G2:G11, "<>") -> 10 | D24: =COUNTIF('Admin - Setup'!G2:G11, "Pass") -> 0 | E24: =COUNTIF('Admin - Setup'!G2:G11, "Fail") -> 0 | F24: =COUNTIF('Admin - Setup'!G2:G11, "Unknown") -> 10 | G24: =IF((D24+E24)>0, D24/(D24+E24), 0) -> 0 | H24: Church branding, contact details, service times management, FAQs CRUD, ministries provisioning
A25: Sitewide Chat | B25: Global Widget | C25: =COUNTIF('Sitewide Chat'!G2:G11, "<>") -> 10 | D25: =COUNTIF('Sitewide Chat'!G2:G11, "Pass") -> 0 | E25: =COUNTIF('Sitewide Chat'!G2:G11, "Fail") -> 0 | F25: =COUNTIF('Sitewide Chat'!G2:G11, "Unknown") -> 10 | G25: =IF((D25+E25)>0, D25/(D25+E25), 0) -> 0 | H25: Chat launcher, starter pills, scheduled event queries, volunteer inquiry, prayer request handoff
A26: Suite Total / Rollup | B26: All 17 Areas | C26: =SUM(C9:C25) -> 180 | D26: =SUM(D9:D25) -> 0 | E26: =SUM(E9:E25) -> 0 | F26: =SUM(F9:F25) -> 180 | G26: =IF((D26+E26)>0, D26/(D26+E26), 0) -> 0 | H26: Dynamic rollup tracking user-tested execution progress across all 17 page sheets

Sheet All Test Cases
A1: Name of Test Case | B1: Category | C1: Name of Page | D1: Action to Take | E1: Expected Outcome | F1: Outcome/Result | G1: Pass/Fail
A2: ='Agentic Builder'!A2 -> Ask AI to change pastor name | B2: ='Agentic Builder'!B2 -> Natural Language Editing | C2: ='Agentic Builder'!C2 -> Builder | D2: ='Agentic Builder'!D2 -> In review screen or preview banner, enter 'Change pastor name to Pastor John Mark' into Tekton edit box and click 'Change it'. | E2: ='Agentic Builder'!E2 -> Agent identifies lead pastor in staff collection, updates name to 'Pastor John Mark', confirms with 'Changed pastor to Pastor John Mark', and increments undo count. | F2: ='Agentic Builder'!F2 | G2: ='Agentic Builder'!G2 -> Unknown
A3: ='Agentic Builder'!A3 -> Reorder sections: Put service times above ministries | B3: ='Agentic Builder'!B3 -> Natural Language Layout | C3: ='Agentic Builder'!C3 -> Builder | D3: ='Agentic Builder'!D3 -> Type 'Put service times above ministries' in Tekton edit box and click 'Change it'. | E3: ='Agentic Builder'!E3 -> Deterministic layout rule detects service_times and ministries on Home, moves service times before ministries, and confirms 'Moved Service times on Home above Ministries'. | F3: ='Agentic Builder'!F3 | G3: ='Agentic Builder'!G3 -> Unknown
A4: ='Agentic Builder'!A4 -> Hide specific ministry: Hide the youth ministry | B4: ='Agentic Builder'!B4 -> Natural Language Visibility | C4: ='Agentic Builder'!C4 -> Builder | D4: ='Agentic Builder'!D4 -> Type 'Hide the youth ministry' into Tekton edit input and click 'Change it'. | E4: ='Agentic Builder'!E4 -> Agent matches 'Youth Ministry' in ministries collection, sets include: false, and replies 'Left out Youth Ministry'. | F4: ='Agentic Builder'!F4 | G4: ='Agentic Builder'!G4 -> Unknown
A5: ='Agentic Builder'!A5 -> Move section to top: Move what to expect to the top | B5: ='Agentic Builder'!B5 -> Natural Language Layout | C5: ='Agentic Builder'!C5 -> Builder | D5: ='Agentic Builder'!D5 -> Type 'Move what to expect to the top' into Tekton edit input and click 'Change it'. | E5: ='Agentic Builder'!E5 -> Layout engine moves what_to_expect section on Plan your visit page to index 0 and replies 'Moved What to expect on Plan your visit to the top'. | F5: ='Agentic Builder'!F5 | G5: ='Agentic Builder'!G5 -> Unknown
A6: ='Agentic Builder'!A6 -> Update church phone number via plain text command | B6: ='Agentic Builder'!B6 -> Natural Language Detail Update | C6: ='Agentic Builder'!C6 -> Builder | D6: ='Agentic Builder'!D6 -> Type 'Change the phone number to (555) 019-9988' into Tekton edit input and click 'Change it'. | E6: ='Agentic Builder'!E6 -> Agent parses new phone format, validates number, updates church contact phone field, and replies 'Changed phone to (555) 019-9988'. | F6: ='Agentic Builder'!F6 | G6: ='Agentic Builder'!G6 -> Unknown
A7: ='Agentic Builder'!A7 -> Undo previous edit operation | B7: ='Agentic Builder'!B7 -> Revision Control | C7: ='Agentic Builder'!C7 -> Builder | D7: ='Agentic Builder'!D7 -> Click 'Undo' button after executing a section reordering or detail change. | E7: ='Agentic Builder'!E7 -> Restores previous draft snapshot state from undo stack, decrements undo count, and announces reversed changes. | F7: ='Agentic Builder'!F7 | G7: ='Agentic Builder'!G7 -> Unknown
A8: ='Agentic Builder'!A8 -> Import website from live URL (Happy path crawl) | B8: ='Agentic Builder'!B8 -> URL Crawl & Ingestion | C8: ='Agentic Builder'!C8 -> Builder | D8: ='Agentic Builder'!D8 -> Select 'Import a website', enter 'https://cedarhollow.example.org', and click 'Start import'. | E8: ='Agentic Builder'!E8 -> Crawler reads sitemap and top pages within robots.txt limits, extracts name, address, phone, email, and service times with 0 false conflicts, and transitions to review. | F8: ='Agentic Builder'!F8 | G8: ='Agentic Builder'!G8 -> Unknown
A9: ='Agentic Builder'!A9 -> Detect conflicting service times from messy site | B9: ='Agentic Builder'!B9 -> Conflict Detection | C9: ='Agentic Builder'!C9 -> Builder | D9: ='Agentic Builder'!D9 -> Import URL containing conflicting times: 'Sundays 9 & 11' on home page and 'Sunday 10:30am' on news post. | E9: ='Agentic Builder'!E9 -> Draft status transitions to clarifying; displays conflict question card showing both candidate times with verbatim source quotes and page links. | F9: ='Agentic Builder'!F9 | G9: ='Agentic Builder'!G9 -> Unknown
A10: ='Agentic Builder'!A10 -> Resolve service time conflict by picking candidate card | B10: ='Agentic Builder'!B10 -> Human Clarification Flow | C10: ='Agentic Builder'!C10 -> Builder | D10: ='Agentic Builder'!D10 -> On service times conflict card, click candidate 'Sunday 9:00 AM, Sunday 11:00 AM' and click 'Confirm answer'. | E10: ='Agentic Builder'!E10 -> Selected service times are locked into confirmed status with provenance attribution; builder advances to next question or review. | F10: ='Agentic Builder'!F10 | G10: ='Agentic Builder'!G10 -> Unknown
A11: ='Agentic Builder'!A11 -> Prompt for missing required address and accept manual input | B11: ='Agentic Builder'!B11 -> Gap Detection & Form Validation | C11: ='Agentic Builder'!C11 -> Builder | D11: ='Agentic Builder'!D11 -> When presented with 'We could not find street address', type '100 Faith Way, Springfield, IL 62701' into input and submit. | E11: ='Agentic Builder'!E11 -> Manual address entry is validated, saved to draft with confirmed status ('You confirmed this'), and question resolves. | F11: ='Agentic Builder'!F11 | G11: ='Agentic Builder'!G11 -> Unknown
A12: ='Agentic Builder'!A12 -> Ingest PDF church bulletin and extract facts | B12: ='Agentic Builder'!B12 -> Document Extraction - PDF | C12: ='Agentic Builder'!C12 -> Builder | D12: ='Agentic Builder'!D12 -> Select 'Upload files', drag and drop a 2 MB weekly church bulletin PDF containing service times and pastor bio, and click 'Read files'. | E12: ='Agentic Builder'!E12 -> Server parses PDF text streams, applies NLP regex patterns, extracts service times and staff items, and displays quotes referencing PDF filename. | F12: ='Agentic Builder'!F12 | G12: ='Agentic Builder'!G12 -> Unknown
A13: ='Agentic Builder'!A13 -> Ingest church flyer image via Vision AI OCR | B13: ='Agentic Builder'!B13 -> Multimodal Vision Extraction | C13: ='Agentic Builder'!C13 -> Builder | D13: ='Agentic Builder'!D13 -> Upload church flyer image (JPEG/PNG) displaying worship schedule and logo. | E13: ='Agentic Builder'!E13 -> Vision AI transcribes image text into machine-readable prose; rules parser extracts church schedule and logo reference. | F13: ='Agentic Builder'!F13 | G13: ='Agentic Builder'!G13 -> Unknown
... A21: ='Agentic Builder'!A21 -> Publish live production church without invite code | B21: ='Agentic Builder'!B21 -> Tenant Provisioning Guardrail | C21: ='Agentic Builder'!C21 -> Builder | D21: ='Agentic Builder'!D21 -> On preview screen, attempt to provision and deploy a new live church tenant without entering an invite code. | E21: ='Agentic Builder'!E21 -> System provisions new church tenant and deploys public domain. | F21: ='Agentic Builder'!F21 | G21: ='Agentic Builder'!G21 -> Unknown
A22: =Home!A2 -> Hero CTA: Find a place to serve button | B22: =Home!B2 -> Navigation & User Flow | C22: =Home!C2 -> Home | D22: =Home!D2 -> Click 'Find a place to serve' primary button on the hero banner. | E22: =Home!E2 -> Application navigates directly to '#/serve/find' volunteer matching page. | F22: =Home!F2 | G22: =Home!G2 -> Unknown
A23: =Home!A3 -> Hero CTA: Planning your first visit button | B23: =Home!B3 -> Navigation & User Flow | C23: =Home!C3 -> Home | D23: =Home!D3 -> Click 'Planning your first visit?' secondary button on the hero banner. | E23: =Home!E3 -> Application navigates directly to '#/guests/plan' first-time guest page. | F23: =Home!F3 | G23: =Home!G3 -> Unknown
A24: =Home!A4 -> Hero CTA: Ask Tekton chat launcher | B24: =Home!B4 -> AI Assistant Integration | C24: =Home!C4 -> Home | D24: =Home!D4 -> Click 'Ask Tekton' button with chat icon in the hero banner. | E24: =Home!E4 -> Sitewide chat assistant drawer slides open from right with greeting message. | F24: =Home!F4 | G24: =Home!G4 -> Unknown
A25: =Home!A5 -> Serve feature card navigation | B25: =Home!B5 -> Feature Card Routing | C25: =Home!C5 -> Home | D25: =Home!D5 -> Click 'Serve' feature card in the main features grid. | E25: =Home!E5 -> Navigates to '#/serve' ministries directory overview page. | F25: =Home!F5 | G25: =Home!G5 -> Unknown
A26: =Home!A6 -> Sermon Notes feature card navigation | B26: =Home!B6 -> Feature Card Routing | C26: =Home!C6 -> Home | D26: =Home!D6 -> Click 'Sermon Notes' feature card in the main features grid. | E26: =Home!E6 -> Navigates to '#/notes' sermon notes transcript archive. | F26: =Home!F6 | G26: =Home!G6 -> Unknown
A27: =Home!A7 -> Give feature card goal progress bar display | B27: =Home!B7 -> Fundraising Goal Tracking | C27: =Home!C7 -> Home | D27: =Home!D7 -> Inspect Give feature card when a church fund has an active fundraising goal. | E27: =Home!E7 -> Card displays fund name, raised amount, goal amount, and accurately styled visual percentage progress bar. | F27: =Home!F7 | G27: =Home!G7 -> Unknown
A28: =Home!A8 -> Get to know us directory quick button | B28: =Home!B8 -> Quick Links Navigation | C28: =Home!C8 -> Home | D28: =Home!D8 -> Click 'Contact directory' button in the 'Get to know us' section. | E28: =Home!E8 -> Navigates directly to '#/about/directory' staff contact listing. | F28: =Home!F8 | G28: =Home!G8 -> Unknown
A29: =Home!A9 -> Service times and address card rendering | B29: =Home!B9 -> Visitor Information | C29: =Home!C9 -> Home | D29: =Home!D9 -> Inspect 'Service times' block on the Home page. | E29: =Home!E9 -> Displays weekly gathering schedule (e.g. 'Sunday 9:00 AM & 11:00 AM') and church physical address with location pin icon. | F29: =Home!F9 | G29: =Home!G9 -> Unknown
A30: =Home!A10 -> Watch Live external link when livestream is unconfigured | B30: =Home!B10 -> Livestream Integration | C30: =Home!C10 -> Home | D30: =Home!D10 -> Click 'Watch live' hero action button when church has no active livestream URL configured. | E30: =Home!E10 -> Displays friendly popup indicating no active broadcast is currently streaming. | F30: =Home!F10 | G30: =Home!G10 -> Unknown
A31: =Home!A11 -> Hero about text rendering on new unconfigured church | B31: =Home!B11 -> Tenant Onboarding Display | C31: =Home!C11 -> Home | D31: =Home!D11 -> Open Home page for newly provisioned church with no about description provided. | E31: =Home!E11 -> Displays elegant onboarding prompt guiding visitors and staff to add story. | F31: =Home!F11 | G31: =Home!G11 -> Unknown
A32: ='Plan Your Visit'!A2 -> Submit guest visit RSVP registration form | B32: ='Plan Your Visit'!B2 -> Guest Registration Flow | C32: ='Plan Your Visit'!C2 -> Guests - Plan Your Visit | D32: ='Plan Your Visit'!D2 -> Fill in name 'Sarah Jenkins', contact 'sarah@example.org', select 'Sunday 9:00 AM', party size 3, and click 'Let us know you’re coming'. | E32: ='Plan Your Visit'!E2 -> Form submits to POST /api/visits, receives visit token, saves token to localStorage, and updates UI to registered state. | F32: ='Plan Your Visit'!F2 | G32: ='Plan Your Visit'!G2 -> Unknown
A33: ='Plan Your Visit'!A3 -> Validate required fields in visit registration | B33: ='Plan Your Visit'!B3 -> Form Validation | C33: ='Plan Your Visit'!C3 -> Guests - Plan Your Visit | D33: ='Plan Your Visit'!D3 -> Leave name and contact fields blank and click 'Let us know you’re coming'. | E33: ='Plan Your Visit'!E3 -> Browser displays HTML5 validation prompt on required name and contact inputs; submission is halted. | F33: ='Plan Your Visit'!F3 | G33: ='Plan Your Visit'!G3 -> Unknown
A34: ='Plan Your Visit'!A4 -> Select service time from dynamic dropdown | B34: ='Plan Your Visit'!B4 -> Form Interaction | C34: ='Plan Your Visit'!C4 -> Guests - Plan Your Visit | D34: ='Plan Your Visit'!D4 -> Click service time dropdown and select second gathering 'Sunday 11:00 AM'. | E34: ='Plan Your Visit'!E4 -> Selected service time state updates and is included in the visit payload. | F34: ='Plan Your Visit'!F4 | G34: ='Plan Your Visit'!G4 -> Unknown
A35: ='Plan Your Visit'!A5 -> Toggle 'I’d like someone to meet me' host checkbox | B35: ='Plan Your Visit'!B5 -> Hospitality Preferences | C35: ='Plan Your Visit'!C5 -> Guests - Plan Your Visit | D35: ='Plan Your Visit'!D5 -> Uncheck the 'I’d like someone to meet me at the front doors' checkbox. | E35: ='Plan Your Visit'!E5 -> wantsHost state sets to false; submitted visit payload reflects 'wants_host: false'. | F35: ='Plan Your Visit'!F5 | G35: ='Plan Your Visit'!G5 -> Unknown
A36: ='Plan Your Visit'!A6 -> Click 'I’m on my way' arrival notification button | B36: ='Plan Your Visit'!B6 -> Guest Arrival Flow | C36: ='Plan Your Visit'!C6 -> Guests - Plan Your Visit | D36: ='Plan Your Visit'!D6 -> On the confirmed visit card, click 'I’m on my way' button. | E36: ='Plan Your Visit'!E6 -> Visits API updates status to 'on_the_way'; welcome team queue receives live status update. | F36: ='Plan Your Visit'!F6 | G36: ='Plan Your Visit'!G6 -> Unknown
A37: ='Plan Your Visit'!A7 -> Click 'I have arrived' check-in button | B37: ='Plan Your Visit'!B7 -> Guest Arrival Flow | C37: ='Plan Your Visit'!C7 -> Guests - Plan Your Visit | D37: ='Plan Your Visit'!D7 -> On confirmed visit card, click 'I have arrived' button. | E37: ='Plan Your Visit'!E7 -> Visits API updates status to 'arrived'; triggers desktop notification on welcome team workstation. | F37: ='Plan Your Visit'!F7 | G37: ='Plan Your Visit'!G7 -> Unknown
A38: ='Plan Your Visit'!A8 -> Expand FAQ accordion to read answer | B38: ='Plan Your Visit'!B8 -> Content Disclosure | C38: ='Plan Your Visit'!C8 -> Guests - Plan Your Visit | D38: ='Plan Your Visit'!D8 -> Click on question 'What should I wear?' in the FAQ section. | E38: ='Plan Your Visit'!E8 -> Accordion item expands revealing helpful answer about casual attire. | F38: ='Plan Your Visit'!F8 | G38: ='Plan Your Visit'!G8 -> Unknown
A39: ='Plan Your Visit'!A9 -> Open Google Maps directions link | B39: ='Plan Your Visit'!B9 -> External Navigation | C39: ='Plan Your Visit'!C9 -> Guests - Plan Your Visit | D39: ='Plan Your Visit'!D9 -> Click 'Get directions' button next to the church address. | E39: ='Plan Your Visit'!E9 -> Opens Google Maps search query with church street address in new browser tab. | F39: ='Plan Your Visit'!F9 | G39: ='Plan Your Visit'!G9 -> Unknown
A40: ='Plan Your Visit'!A10 -> Interactive parking spot selection on mobile Safari touchscreens | B40: ='Plan Your Visit'!B10 -> Touchscreen Mapping | C40: ='Plan Your Visit'!C10 -> Guests - Plan Your Visit | D40: ='Plan Your Visit'!D10 -> Tap parking spot on campus SVG map using an iOS Safari mobile browser. | E40: ='Plan Your Visit'!E10 -> Spot highlights and selection binds to form payload. | F40: ='Plan Your Visit'!F10 | G40: ='Plan Your Visit'!G10 -> Unknown
A41: ='Plan Your Visit'!A11 -> Guest RSVP submission with international phone number format | B41: ='Plan Your Visit'!B11 -> Input Sanitization & Regex | C41: ='Plan Your Visit'!C11 -> Guests - Plan Your Visit | D41: ='Plan Your Visit'!D11 -> Enter international format contact number '+44 20 7946 0958' in RSVP contact field. | E41: ='Plan Your Visit'!E11 -> Validates international phone format and registers visit. | F41: ='Plan Your Visit'!F11 | G41: ='Plan Your Visit'!G11 -> Unknown
A42: ='Welcome Team'!A2 -> Block unauthorized visitor access to welcome queue | B42: ='Welcome Team'!B2 -> Access Control | C42: ='Welcome Team'!C2 -> Guests - Welcome Team | D42: ='Welcome Team'!D2 -> Navigate to '#/guests/welcome' as an unauthenticated public visitor. | E42: ='Welcome Team'!E2 -> Welcome queue is hidden; displays 'StaffOnly' notice prompting staff sign-in. | F42: ='Welcome Team'!F2 | G42: ='Welcome Team'!G2 -> Unknown
A43: ='Welcome Team'!A3 -> Display arrived guests queue for signed-in staff | B43: ='Welcome Team'!B3 -> Queue Visibility | C43: ='Welcome Team'!C3 -> Guests - Welcome Team | D43: ='Welcome Team'!D3 -> Sign in as staff and open '#/guests/welcome'. | E43: ='Welcome Team'!E3 -> Displays WelcomeQueue component showing waiting list and planned guests list. | F43: ='Welcome Team'!F3 | G43: ='Welcome Team'!G3 -> Unknown
A44: ='Welcome Team'!A4 -> Persist host staff name in local storage | B44: ='Welcome Team'!B4 -> Host Identity | C44: ='Welcome Team'!C4 -> Guests - Welcome Team | D44: ='Welcome Team'!D4 -> Type host name 'Brother David' into 'Your name' field and reload page. | E44: ='Welcome Team'!E4 -> Host name 'Brother David' is saved to localStorage and restored on reload. | F44: ='Welcome Team'!F4 | G44: ='Welcome Team'!G4 -> Unknown
A45: ='Welcome Team'!A5 -> Claim an arrived guest from waiting queue | B45: ='Welcome Team'!B5 -> Host Assignment | C45: ='Welcome Team'!C5 -> Guests - Welcome Team | D45: ='Welcome Team'!D5 -> Click 'I’ll meet them' button on a waiting guest card. | E45: ='Welcome Team'!E5 -> Calls POST /visits/:id/claim with hostName; marks guest as claimed by Brother David. | F45: ='Welcome Team'!F5 | G45: ='Welcome Team'!G5 -> Unknown
A46: ='Welcome Team'!A6 -> Dismiss welcomed guest from queue | B46: ='Welcome Team'!B6 -> Status Lifecycle | C46: ='Welcome Team'!C6 -> Guests - Welcome Team | D46: ='Welcome Team'!D6 -> Click 'Welcomed' checkmark button on a claimed guest card. | E46: ='Welcome Team'!E6 -> Calls PATCH /visits/:id with status 'welcomed'; removes guest from active waiting list. | F46: ='Welcome Team'!F6 | G46: ='Welcome Team'!G6 -> Unknown
A47: ='Welcome Team'!A7 -> Display accurate party size and host preference tags | B47: ='Welcome Team'!B7 -> Metadata Rendering | C47: ='Welcome Team'!C7 -> Guests - Welcome Team | D47: ='Welcome Team'!D7 -> Inspect waiting guest card for party of 4 who prefers not to be met. | E47: ='Welcome Team'!E7 -> Card displays 'Party of 4' badge and muted notice 'Prefers not to be met at door'. | F47: ='Welcome Team'!F7 | G47: ='Welcome Team'!G7 -> Unknown
A48: ='Welcome Team'!A8 -> Display elapsed waiting time counter | B48: ='Welcome Team'!B8 -> Queue Metrics | C48: ='Welcome Team'!C8 -> Guests - Welcome Team | D48: ='Welcome Team'!D8 -> Observe waiting guest card for guest who arrived 6 minutes ago. | E48: ='Welcome Team'!E8 -> Displays elapsed waiting counter 'Arrived 6m ago' updating periodically. | F48: ='Welcome Team'!F8 | G48: ='Welcome Team'!G8 -> Unknown
A49: ='Welcome Team'!A9 -> Real-time queue polling updates without refresh | B49: ='Welcome Team'!B9 -> Real-time Synchronization | C49: ='Welcome Team'!C9 -> Guests - Welcome Team | D49: ='Welcome Team'!D9 -> Keep Welcome Team screen open while a new guest checks in on another device. | E49: ='Welcome Team'!E9 -> Background 5-second interval poll detects new arrival and adds card to queue with arrival chime/alert. | F49: ='Welcome Team'!F9 | G49: ='Welcome Team'!G9 -> Unknown
A50: ='Welcome Team'!A10 -> Browser arrival push notifications on mobile browsers (iOS / Android) | B50: ='Welcome Team'!B10 -> Web Push Notifications | C50: ='Welcome Team'!C10 -> Guests - Welcome Team | D50: ='Welcome Team'!D10 -> Tap 'Enable arrival notifications' on iOS Safari or mobile web browser. | E50: ='Welcome Team'!E10 -> Native browser arrival push notifications fire when guest arrives. | F50: ='Welcome Team'!F10 | G50: ='Welcome Team'!G10 -> Unknown
A51: ='Welcome Team'!A11 -> Concurrent guest claim race condition between two hosts | B51: ='Welcome Team'!B11 -> Concurrency & Locking | C51: ='Welcome Team'!C11 -> Guests - Welcome Team | D51: ='Welcome Team'!D11 -> Two welcome hosts click 'I’ll meet them' on the same arrived guest card within 1 second. | E51: ='Welcome Team'!E11 -> Optimistic concurrency lock notifies second host that guest was already claimed by another team member. | F51: ='Welcome Team'!F11 | G51: ='Welcome Team'!G11 -> Unknown
A52: =Serve!A2 -> Filter serving teams by keyword search | B52: =Serve!B2 -> Search & Filtering | C52: =Serve!C2 -> Serve | D52: =Serve!D2 -> Type 'worship' into ministry search input field. | E52: =Serve!E2 -> List filters instantly to ministries containing 'worship' in name, description, or category. | F52: =Serve!F2 | G52: =Serve!G2 -> Unknown
A53: =Serve!A3 -> Toggle 'Urgent needs only' filter checkbox | B53: =Serve!B3 -> Urgency Triage | C53: =Serve!C3 -> Serve | D53: =Serve!D3 -> Click 'Urgent needs only' filter button. | E53: =Serve!E3 -> Displays only ministries where unfilled volunteer slots are 35% or higher, with urgent badge. | F53: =Serve!F3 | G53: =Serve!G3 -> Unknown
A54: =Serve!A4 -> Expand ministry card to inspect team leader and roles | B54: =Serve!B4 -> Detail Disclosure | C54: =Serve!C4 -> Serve | D54: =Serve!D4 -> Click on 'Kids Ministry' card in the serving grid. | E54: =Serve!E4 -> Detailed drawer opens showing team description, time commitments, and ministry leader contact. | F54: =Serve!F4 | G54: =Serve!G4 -> Unknown
A55: =Serve!A5 -> Bookmark recommended ministry to saved shortlist | B55: =Serve!B5 -> Shortlist Management | C55: =Serve!C5 -> Serve | D55: =Serve!D5 -> Click 'Save to shortlist' bookmark icon on 'Worship Collective' recommendation card. | E55: =Serve!E5 -> Ministry is added to local saved list; navigation badge count increments by 1. | F55: =Serve!F5 | G55: =Serve!G5 -> Unknown
A56: =Serve!A6 -> View saved ministries tab | B56: =Serve!B6 -> Shortlist Review | C56: =Serve!C6 -> Serve | D56: =Serve!D6 -> Click 'Saved' sub-navigation tab ('#/serve/saved'). | E56: =Serve!E6 -> Displays all bookmarked serving opportunities with option to submit interest request. | F56: =Serve!F6 | G56: =Serve!G6 -> Unknown
A57: =Serve!A7 -> Staff view of filed volunteer connection requests | B57: =Serve!B7 -> Staff Queue Management | C57: =Serve!C7 -> Serve | D57: =Serve!D7 -> Sign in as staff and open '#/serve/saved' requests queue. | E57: =Serve!E7 -> Staff sees full list of member-submitted volunteer inquiries and chat connection requests. | F57: =Serve!F7 | G57: =Serve!G7 -> Unknown
A58: =Serve!A8 -> Staff approves volunteer connection request | B58: =Serve!B8 -> Workflow State Change | C58: =Serve!C8 -> Serve | D58: =Serve!D8 -> Click 'Connect' checkmark button on a pending volunteer request. | E58: =Serve!E8 -> Calls PATCH /requests/:id with status 'connected'; moves request to active connections list. | F58: =Serve!F8 | G58: =Serve!G8 -> Unknown
A59: =Serve!A9 -> Staff archives or deletes processed request | B59: =Serve!B9 -> Queue Cleanup | C59: =Serve!C9 -> Serve | D59: =Serve!D9 -> Click 'Remove' trash icon on an archived volunteer request. | E59: =Serve!E9 -> Calls DELETE /requests/:id; removes request card from staff queue view. | F59: =Serve!F9 | G59: =Serve!G9 -> Unknown
A60: =Serve!A10 -> AI volunteer matching with single-word generic input | B60: =Serve!B10 -> AI Recommendation Bounds | C60: =Serve!C10 -> Serve | D60: =Serve!D10 -> On volunteer finder, enter single word 'anything' into gifts input and click 'Find matching places'. | E60: =Serve!E10 -> Prompts user to specify gifts/skills or provides general serving opportunities. | F60: =Serve!F10 | G60: =Serve!G10 -> Unknown
A61: =Serve!A11 -> Real-time staff queue update across multiple browser sessions | B61: =Serve!B11 -> Cross-client Synchronization | C61: =Serve!C11 -> Serve | D61: =Serve!D11 -> Visitor files a volunteer request in chat; observe staff queue on a separate un-refreshed staff browser. | E61: =Serve!E11 -> Staff queue updates automatically via WebSocket or background push without manual reload. | F61: =Serve!F11 | G61: =Serve!G11 -> Unknown
A62: ='Sermon Notes'!A2 -> Browse sermon catalog and open message | B62: ='Sermon Notes'!B2 -> Content Discovery | C62: ='Sermon Notes'!C2 -> Sermon Notes | D62: ='Sermon Notes'!D2 -> Click on sermon card 'The Heart of the Father - Luke 15' in sermon list. | E62: ='Sermon Notes'!E2 -> Navigates to '#/notes/:id'; loads full sermon transcript, media player, and AI ask panel. | F62: ='Sermon Notes'!F2 | G62: ='Sermon Notes'!G2 -> Unknown
A63: ='Sermon Notes'!A3 -> Ask AI question about sermon content | B63: ='Sermon Notes'!B3 -> AI Sermon Q&A | C63: ='Sermon Notes'!C3 -> Sermon Notes | D63: ='Sermon Notes'!D3 -> In sermon ask box, type 'What did the pastor say about the older brother?' and click Ask. | E63: ='Sermon Notes'!E3 -> AI queries sermon embeddings, returns answer summarizing pastor's points, and quotes verbatim sentences with timestamps. | F63: ='Sermon Notes'!F3 | G63: ='Sermon Notes'!G3 -> Unknown
A64: ='Sermon Notes'!A4 -> Click transcript timestamp to seek media player | B64: ='Sermon Notes'!B4 -> Media Synchronization | C64: ='Sermon Notes'!C4 -> Sermon Notes | D64: ='Sermon Notes'!D4 -> Click timestamp link '[14:32]' inside sermon transcript text. | E64: ='Sermon Notes'!E4 -> Audio/video player seeks immediately to 14 minutes 32 seconds and starts playback. | F64: ='Sermon Notes'!F4 | G64: ='Sermon Notes'!G4 -> Unknown
A65: ='Sermon Notes'!A5 -> Toggle 'Bible quotes' highlight filter | B65: ='Sermon Notes'!B5 -> Transcript Annotation | C65: ='Sermon Notes'!C5 -> Sermon Notes | D65: ='Sermon Notes'!D5 -> Click 'Bible quotes' button in highlight categories toggle bar. | E65: ='Sermon Notes'!E5 -> All direct Scripture quotations in transcript highlight with gold background styling. | F65: ='Sermon Notes'!F5 | G65: ='Sermon Notes'!G5 -> Unknown
A66: ='Sermon Notes'!A6 -> Tap scripture highlight to open YouVersion verse card | B66: ='Sermon Notes'!B6 -> Scripture Integration | C66: ='Sermon Notes'!C6 -> Sermon Notes | D66: ='Sermon Notes'!D6 -> Click highlighted Bible reference 'Romans 8:28' in sermon transcript. | E66: ='Sermon Notes'!E6 -> VerseCard popover opens displaying full text of Romans 8:28 fetched from Bible API. | F66: ='Sermon Notes'!F6 | G66: ='Sermon Notes'!G6 -> Unknown
A67: ='Sermon Notes'!A7 -> Switch preferred Bible translation in reader preferences | B67: ='Sermon Notes'!B7 -> User Preferences | C67: ='Sermon Notes'!C7 -> Sermon Notes | D67: ='Sermon Notes'!D7 -> Open reader settings and change translation from NIV to ESV. | E67: ='Sermon Notes'!E7 -> Passage references reload with English Standard Version text; preference saved to localStorage. | F67: ='Sermon Notes'!F7 | G67: ='Sermon Notes'!G7 -> Unknown
A68: ='Sermon Notes'!A8 -> Adjust transcript font size for accessibility | B68: ='Sermon Notes'!B8 -> Accessibility & Display | C68: ='Sermon Notes'!C8 -> Sermon Notes | D68: ='Sermon Notes'!D8 -> Click font size '+' button in reader toolbar. | E68: ='Sermon Notes'!E8 -> Transcript body text size increases from 16px to 19px for enhanced readability. | F68: ='Sermon Notes'!F8 | G68: ='Sermon Notes'!G8 -> Unknown
A69: ='Sermon Notes'!A9 -> Staff creates new sermon note via YouTube URL | B69: ='Sermon Notes'!B9 -> Media Ingestion - YouTube | C69: ='Sermon Notes'!C9 -> Sermon Notes | D69: ='Sermon Notes'!D9 -> Sign in as staff, click '+ New note', enter valid YouTube link, title 'Sunday Service', and click 'Create note'. | E69: ='Sermon Notes'!E9 -> Backend queues YouTube audio download and Whisper transcription job; sermon status becomes 'queued'. | F69: ='Sermon Notes'!F9 | G69: ='Sermon Notes'!G9 -> Unknown
A70: ='Sermon Notes'!A10 -> Process sermon video with bot-protected YouTube URL | B70: ='Sermon Notes'!B10 -> Media Ingestion - YouTube | C70: ='Sermon Notes'!C10 -> Sermon Notes | D70: ='Sermon Notes'!D10 -> Submit a YouTube sermon URL that requires bot challenge or sign-in verification. | E70: ='Sermon Notes'!E10 -> System bypasses bot challenge and downloads audio for transcription. | F70: ='Sermon Notes'!F10 | G70: ='Sermon Notes'!G10 -> Unknown
A71: ='Sermon Notes'!A11 -> Upload video file exceeding 95 MB limit | B71: ='Sermon Notes'!B11 -> File Upload Validation | C71: ='Sermon Notes'!C11 -> Sermon Notes | D71: ='Sermon Notes'!D11 -> Attach 120 MB MP4 sermon recording and click 'Create note'. | E71: ='Sermon Notes'!E11 -> Client-side file validation prevents upload and shows clear file size guidance. | F71: ='Sermon Notes'!F11 | G71: ='Sermon Notes'!G11 -> Unknown
A72: =Calendar!A2 -> Toggle between monthly calendar grid and upcoming list view | B72: =Calendar!B2 -> View Mode Switching | C72: =Calendar!C2 -> Calendar | D72: =Calendar!D2 -> Click 'List view' button in the calendar toolbar. | E72: =Calendar!E2 -> Display changes from 7-day monthly grid to chronological list view grouped by date. | F72: =Calendar!F2 | G72: =Calendar!G2 -> Unknown
A73: =Calendar!A3 -> Filter calendar events by category | B73: =Calendar!B3 -> Category Filtering | C73: =Calendar!C3 -> Calendar | D73: =Calendar!D3 -> Click category filter button 'Youth & Kids'. | E73: =Calendar!E3 -> Calendar highlights/shows only events tagged with 'Youth & Kids' category. | F73: =Calendar!F3 | G73: =Calendar!G3 -> Unknown
A74: =Calendar!A4 -> Search calendar gatherings by keyword | B74: =Calendar!B4 -> Keyword Search | C74: =Calendar!C4 -> Calendar | D74: =Calendar!D4 -> Type 'prayer' into calendar search bar. | E74: =Calendar!E4 -> Filters calendar display to events containing 'prayer' in title or description. | F74: =Calendar!F4 | G74: =Calendar!G4 -> Unknown
A75: =Calendar!A5 -> Navigate across calendar months | B75: =Calendar!B5 -> Date Navigation | C75: =Calendar!C5 -> Calendar | D75: =Calendar!D5 -> Click 'Next month' arrow button in calendar header. | E75: =Calendar!E5 -> Calendar advances to next month (e.g. November 2026); fetches and displays that month's events. | F75: =Calendar!F5 | G75: =Calendar!G5 -> Unknown
A76: =Calendar!A6 -> Inspect event detail modal by clicking calendar cell | B76: =Calendar!B6 -> Event Inspection | C76: =Calendar!C6 -> Calendar | D76: =Calendar!D6 -> Click on 'Community Outreach Day' event entry in the grid. | E76: =Calendar!E6 -> Event detail modal opens showing date, time, location, host ministry, and full event description. | F76: =Calendar!F6 | G76: =Calendar!G6 -> Unknown
A77: =Calendar!A7 -> Staff opens '+ Add event' modal and creates new event | B77: =Calendar!B7 -> Event Creation | C77: =Calendar!C7 -> Calendar | D77: =Calendar!D7 -> Sign in as staff, click '+ Add event', fill in title 'Church Picnic', date, time, location, and click Save. | E77: =Calendar!E7 -> Calls POST /events with event JSON; returns created event; reloads calendar with new item visible. | F77: =Calendar!F7 | G77: =Calendar!G7 -> Unknown
A78: =Calendar!A8 -> Validate required fields in event creation form | B78: =Calendar!B8 -> Form Validation | C78: =Calendar!C8 -> Calendar | D78: =Calendar!D8 -> In '+ Add event' modal, leave title empty and click Save. | E78: =Calendar!E8 -> Form validation halts submission; highlights empty title field with required error. | F78: =Calendar!F8 | G78: =Calendar!G8 -> Unknown
A79: =Calendar!A9 -> Staff deletes or cancels scheduled event | B79: =Calendar!B9 -> Event Deletion | C79: =Calendar!C9 -> Calendar | D79: =Calendar!D9 -> Open event detail modal as staff and click 'Delete event' button with confirmation. | E79: =Calendar!E9 -> Calls DELETE /events/:id; event is removed from calendar display. | F79: =Calendar!F9 | G79: =Calendar!G9 -> Unknown
A80: =Calendar!A10 -> Automatic AI bulletin summary generation on event creation | B80: =Calendar!B10 -> AI Content Generation | C80: =Calendar!C10 -> Calendar | D80: =Calendar!D10 -> As staff, create a new calendar event and check for automated AI bulletin summary. | E80: =Calendar!E10 -> AI endpoint generates welcoming 2-sentence bulletin summary. | F80: =Calendar!F10 | G80: =Calendar!G10 -> Unknown
A81: =Calendar!A11 -> Export calendar gatherings to Apple iCal / .ics file | B81: =Calendar!B11 -> Calendar Standards Export | C81: =Calendar!C11 -> Calendar | D81: =Calendar!D11 -> Click 'Add to calendar' / export button on an event detail view. | E81: =Calendar!E11 -> Downloads standardized .ics file for importing into Apple Calendar or Outlook. | F81: =Calendar!F11 | G81: =Calendar!G11 -> Unknown
A82: =Give!A2 -> Select preset donation amount button | B82: =Give!B2 -> Donation Flow | C82: =Give!C2 -> Give | D82: =Give!D2 -> Click preset dollar amount button '$100'. | E82: =Give!E2 -> Donation total updates to '$100.00' and highlights the $100 button. | F82: =Give!F2 | G82: =Give!G2 -> Unknown
A83: =Give!A3 -> Enter custom donation dollar amount with validation | B83: =Give!B3 -> Form Validation | C83: =Give!C3 -> Give | D83: =Give!D3 -> Click 'Custom amount' input, type '150.00', and proceed. | E83: =Give!E3 -> Custom amount input accepts numeric value and sets donation total to $150.00. | F83: =Give!F3 | G83: =Give!G3 -> Unknown
A84: =Give!A4 -> Select designated fund from fund selector dropdown | B84: =Give!B4 -> Fund Allocation | C84: =Give!C4 -> Give | D84: =Give!D4 -> Open fund selector dropdown and choose 'Missions Fund'. | E84: =Give!E4 -> Donation allocation updates to 'Missions Fund'; fund ID included in checkout session request. | F84: =Give!F4 | G84: =Give!G4 -> Unknown
A85: =Give!A5 -> Browse active mission trips on Mission Trips tab | B85: =Give!B5 -> Mission Trips Discovery | C85: =Give!C5 -> Give | D85: =Give!D5 -> Click 'Mission trips' tab ('#/give/trips'). | E85: =Give!E5 -> Displays active mission trips with destination, trip dates, team size, and funding progress bar. | F85: =Give!F5 | G85: =Give!G5 -> Unknown
A86: =Give!A6 -> Click 'Support this trip' to prefill donation fund | B86: =Give!B6 -> Designated Trip Support | C86: =Give!C6 -> Give | D86: =Give!D6 -> Click 'Support this trip' button on Guatemala outreach card. | E86: =Give!E6 -> Navigates to '#/give' with Guatemala mission fund pre-selected in fund dropdown. | F86: =Give!F6 | G86: =Give!G6 -> Unknown
A87: =Give!A7 -> Submit volunteer application to join a mission trip | B87: =Give!B7 -> Trip Volunteer Application | C87: =Give!C7 -> Give | D87: =Give!D7 -> Click 'Apply to go', fill in applicant name, email, skills, and submit application. | E87: =Give!E7 -> Calls POST /trips/:id/apply; submits application for staff review; displays confirmation. | F87: =Give!F7 | G87: =Give!G7 -> Unknown
A88: =Give!A8 -> Access monthly recurring gift management via secure token | B88: =Give!B8 -> Subscription Self-Service | C88: =Give!C8 -> Give | D88: =Give!D8 -> Open manage gift link with valid token ('#/give/manage/:church.:token'). | E88: =Give!E8 -> Loads donor's monthly gift details: amount, designated fund, next billing date, and cancellation action. | F88: =Give!F8 | G88: =Give!G8 -> Unknown
A89: =Give!A9 -> Cancel recurring monthly donation | B89: =Give!B9 -> Subscription Management | C89: =Give!C9 -> Give | D89: =Give!D9 -> On the manage recurring gift screen, click 'Cancel monthly gift' and confirm in prompt. | E89: =Give!E9 -> Calls DELETE /giving/recurring; cancels Stripe subscription; displays cancellation confirmation. | F89: =Give!F9 | G89: =Give!G9 -> Unknown
A90: =Give!A10 -> Direct credit card donation processing in Demo Mode | B90: =Give!B10 -> Payment Processing | C90: =Give!C10 -> Give | D90: =Give!D10 -> Enter donation amount and attempt live credit card payment on demo church ('slug: demo'). | E90: =Give!E10 -> Processes live donation via Stripe payment gateway. | F90: =Give!F10 | G90: =Give!G10 -> Unknown
A91: =Give!A11 -> Monthly recurring donation setup without Stripe Connect | B91: =Give!B11 -> Payment Configuration Prerequisite | C91: =Give!C11 -> Give | D91: =Give!D11 -> Attempt to set up monthly recurring donation on a church that has not connected Stripe. | E91: =Give!E11 -> Monthly recurring option is disabled with clear prerequisite explanation. | F91: =Give!F11 | G91: =Give!G11 -> Unknown
A92: ='Prayer Map'!A2 -> Render interactive Leaflet world map with partner borders | B92: ='Prayer Map'!B2 -> Map Visualization | C92: ='Prayer Map'!C2 -> Prayer Map | D92: ='Prayer Map'!D2 -> Navigate to '#/prayer'. | E92: ='Prayer Map'!E2 -> Leaflet map initializes centered on global partner regions with highlighted country border polygons. | F92: ='Prayer Map'!F2 | G92: ='Prayer Map'!G2 -> Unknown
A93: ='Prayer Map'!A3 -> Click country prayer beacon to inspect prayer focus | B93: ='Prayer Map'!B3 -> Prayer Focus Inspection | C93: ='Prayer Map'!C3 -> Prayer Map | D93: ='Prayer Map'!D3 -> Click pulsing prayer beacon pin located on country 'Nepal'. | E93: ='Prayer Map'!E3 -> Map centers on Nepal; 'prayer-detail' card below map populates with Nepal prayer needs and cultural context. | F93: ='Prayer Map'!F3 | G93: ='Prayer Map'!G3 -> Unknown
A94: ='Prayer Map'!A4 -> Click real news pin to inspect verified headline and date | B94: ='Prayer Map'!B4 -> News Pin Popup | C94: ='Prayer Map'!C4 -> Prayer Map | D94: ='Prayer Map'!D4 -> Click on red news pin marker located in Kenya. | E94: ='Prayer Map'!E4 -> Popup appears displaying verified news headline, publication date, and summary. | F94: ='Prayer Map'!F4 | G94: ='Prayer Map'!G4 -> Unknown
A95: ='Prayer Map'!A5 -> Verify sensitive nation security safeguard hides team coordinates | B95: ='Prayer Map'!B5 -> Security & Anonymization | C95: ='Prayer Map'!C5 -> Prayer Map | D95: ='Prayer Map'!D5 -> Inspect prayer beacon for restricted/sensitive country. | E95: ='Prayer Map'!E5 -> Pulsing beacon displays only country-level centroid; no local address, GPS coordinates, or missionary names are exposed. | F95: ='Prayer Map'!F5 | G95: ='Prayer Map'!G5 -> Unknown
A96: ='Prayer Map'!A6 -> Verify compact labels toggle on dense zoom levels | B96: ='Prayer Map'!B6 -> Label Collision Prevention | C96: ='Prayer Map'!C6 -> Prayer Map | D96: ='Prayer Map'!D6 -> Zoom out map to world overview level. | E96: ='Prayer Map'!E6 -> LabelDensity hook detects potential label collisions and adds 'compact-labels' class to suppress overlapping text. | F96: ='Prayer Map'!F6 | G96: ='Prayer Map'!G6 -> Unknown
A97: ='Prayer Map'!A7 -> Click 'Fit to borders' to re-center partner nations | B97: ='Prayer Map'!B7 -> Map Bounds Ergonomics | C97: ='Prayer Map'!C7 -> Prayer Map | D97: ='Prayer Map'!D7 -> Pan map far off-center and refresh or trigger fit bounds. | E97: ='Prayer Map'!E7 -> Map automatically calculates bounding box of all church mission regions and fits view with 40px padding. | F97: ='Prayer Map'!F7 | G97: ='Prayer Map'!G7 -> Unknown
A98: ='Prayer Map'!A8 -> Filter prayer updates by selected country | B98: ='Prayer Map'!B8 -> Geographic Filtering | C98: ='Prayer Map'!C8 -> Prayer Map | D98: ='Prayer Map'!D8 -> Select country 'Colombia' from partner nations list. | E98: ='Prayer Map'!E8 -> News and prayer requests list below map filters exclusively to items matching Colombia country code. | F98: ='Prayer Map'!F8 | G98: ='Prayer Map'!G8 -> Unknown
A99: ='Prayer Map'!A9 -> Smooth scroll to selected prayer detail card | B99: ='Prayer Map'!B9 -> Interaction Ergonomics | C99: ='Prayer Map'!C9 -> Prayer Map | D99: ='Prayer Map'!D9 -> Click any country beacon on desktop viewport. | E99: ='Prayer Map'!E9 -> Browser smoothly scrolls down to position 'prayer-detail' card into prominent view. | F99: ='Prayer Map'!F9 | G99: ='Prayer Map'!G9 -> Unknown
A100: ='Prayer Map'!A10 -> Map rendering during backend API service outage | B100: ='Prayer Map'!B10 -> Fault Resilience | C100: ='Prayer Map'!C10 -> Prayer Map | D100: ='Prayer Map'!D10 -> Disconnect backend API server and navigate to '#/prayer'. | E100: ='Prayer Map'!E10 -> Map displays cached offline regions with retry option. | F100: ='Prayer Map'!F10 | G100: ='Prayer Map'!G10 -> Unknown
A101: ='Prayer Map'!A11 -> Country beacon precision on small island nations | B101: ='Prayer Map'!B11 -> Geographic Centroid Precision | C101: ='Prayer Map'!C11 -> Prayer Map | D101: ='Prayer Map'!D11 -> Inspect prayer beacon for small archipelagic partner nation (e.g. Fiji). | E101: ='Prayer Map'!E11 -> Beacon pins directly to inhabited land territory. | F101: ='Prayer Map'!F11 | G101: ='Prayer Map'!G11 -> Unknown
A102: ='About - Our Story'!A2 -> Display church mission statement banner | B102: ='About - Our Story'!B2 -> Mission Display | C102: ='About - Our Story'!C2 -> About - Our Story | D102: ='About - Our Story'!D2 -> Navigate to '#/about'. | E102: ='About - Our Story'!E2 -> Displays 'Our mission' card featuring the church's core mission statement in prominent typography. | F102: ='About - Our Story'!F2 | G102: ='About - Our Story'!G2 -> Unknown
A103: ='About - Our Story'!A3 -> Render church narrative story and history paragraphs | B103: ='About - Our Story'!B3 -> Storytelling Content | C103: ='About - Our Story'!C3 -> About - Our Story | D103: ='About - Our Story'!D3 -> Inspect 'Our story' section on About page. | E103: ='About - Our Story'!E3 -> Renders formatted narrative paragraphs detailing church founding, vision, and community impact. | F103: ='About - Our Story'!F3 | G103: ='About - Our Story'!G3 -> Unknown
A104: ='About - Our Story'!A4 -> Inspect core values cards with distinct icons | B104: ='About - Our Story'!B4 -> Core Values | C104: ='About - Our Story'!C4 -> About - Our Story | D104: ='About - Our Story'!D4 -> Inspect 'What we value' grid on About page. | E104: ='About - Our Story'!E4 -> Displays core value cards (e.g. Grace, Community, Service, Scripture) each with distinct icon and description. | F104: ='About - Our Story'!F4 | G104: ='About - Our Story'!G4 -> Unknown
A105: ='About - Our Story'!A5 -> Verify office hours and physical location in visit block | B105: ='About - Our Story'!B5 -> Facility Details | C105: ='About - Our Story'!C5 -> About - Our Story | D105: ='About - Our Story'!D5 -> Inspect 'Find us / Come visit' section on About page. | E105: ='About - Our Story'!E5 -> Displays church street address, office hours, and weekly gathering times. | F105: ='About - Our Story'!F5 | G105: ='About - Our Story'!G5 -> Unknown
A106: ='About - Our Story'!A6 -> Click 'Plan your visit' CTA button | B106: ='About - Our Story'!B6 -> Internal Navigation | C106: ='About - Our Story'!C6 -> About - Our Story | D106: ='About - Our Story'!D6 -> Click 'Plan your visit' primary button at bottom of story page. | E106: ='About - Our Story'!E6 -> Navigates directly to '#/guests/plan' guest visit registration page. | F106: ='About - Our Story'!F6 | G106: ='About - Our Story'!G6 -> Unknown
A107: ='About - Our Story'!A7 -> Click 'What we believe' button to navigate to beliefs tab | B107: ='About - Our Story'!B7 -> Sub-navigation | C107: ='About - Our Story'!C7 -> About - Our Story | D107: ='About - Our Story'!D7 -> Click 'What we believe' secondary button. | E107: ='About - Our Story'!E7 -> Navigates to '#/about/beliefs' statement of faith tab. | F107: ='About - Our Story'!F7 | G107: ='About - Our Story'!G7 -> Unknown
...

Sheet Agentic Builder
A1: Name of Test Case | B1: Category | C1: Name of Page | D1: Action to Take | E1: Expected Outcome | F1: Outcome/Result | G1: Pass/Fail
A2: Ask AI to change pastor name | B2: Natural Language Editing | C2: Builder | D2: In review screen or preview banner, enter 'Change pastor name to Pastor John Mark' into Tekton edit box and click 'Change it'. | E2: Agent identifies lead pastor in staff collection, updates name to 'Pastor John Mark', confirms with 'Changed pastor to Pastor John Mark', and increments undo count. | G2: Unknown
A3: Reorder sections: Put service times above ministries | B3: Natural Language Layout | C3: Builder | D3: Type 'Put service times above ministries' in Tekton edit box and click 'Change it'. | E3: Deterministic layout rule detects service_times and ministries on Home, moves service times before ministries, and confirms 'Moved Service times on Home above Ministries'. | G3: Unknown
A4: Hide specific ministry: Hide the youth ministry | B4: Natural Language Visibility | C4: Builder | D4: Type 'Hide the youth ministry' into Tekton edit input and click 'Change it'. | E4: Agent matches 'Youth Ministry' in ministries collection, sets include: false, and replies 'Left out Youth Ministry'. | G4: Unknown
A5: Move section to top: Move what to expect to the top | B5: Natural Language Layout | C5: Builder | D5: Type 'Move what to expect to the top' into Tekton edit input and click 'Change it'. | E5: Layout engine moves what_to_expect section on Plan your visit page to index 0 and replies 'Moved What to expect on Plan your visit to the top'. | G5: Unknown
A6: Update church phone number via plain text command | B6: Natural Language Detail Update | C6: Builder | D6: Type 'Change the phone number to (555) 019-9988' into Tekton edit input and click 'Change it'. | E6: Agent parses new phone format, validates number, updates church contact phone field, and replies 'Changed phone to (555) 019-9988'. | G6: Unknown
A7: Undo previous edit operation | B7: Revision Control | C7: Builder | D7: Click 'Undo' button after executing a section reordering or detail change. | E7: Restores previous draft snapshot state from undo stack, decrements undo count, and announces reversed changes. | G7: Unknown
A8: Import website from live URL (Happy path crawl) | B8: URL Crawl & Ingestion | C8: Builder | D8: Select 'Import a website', enter 'https://cedarhollow.example.org', and click 'Start import'. | E8: Crawler reads sitemap and top pages within robots.txt limits, extracts name, address, phone, email, and service times with 0 false conflicts, and transitions to review. | G8: Unknown
A9: Detect conflicting service times from messy site | B9: Conflict Detection | C9: Builder | D9: Import URL containing conflicting times: 'Sundays 9 & 11' on home page and 'Sunday 10:30am' on news post. | E9: Draft status transitions to clarifying; displays conflict question card showing both candidate times with verbatim source quotes and page links. | G9: Unknown
A10: Resolve service time conflict by picking candidate card | B10: Human Clarification Flow | C10: Builder | D10: On service times conflict card, click candidate 'Sunday 9:00 AM, Sunday 11:00 AM' and click 'Confirm answer'. | E10: Selected service times are locked into confirmed status with provenance attribution; builder advances to next question or review. | G10: Unknown
A11: Prompt for missing required address and accept manual input | B11: Gap Detection & Form Validation | C11: Builder | D11: When presented with 'We could not find street address', type '100 Faith Way, Springfield, IL 62701' into input and submit. | E11: Manual address entry is validated, saved to draft with confirmed status ('You confirmed this'), and question resolves. | G11: Unknown
A12: Ingest PDF church bulletin and extract facts | B12: Document Extraction - PDF | C12: Builder | D12: Select 'Upload files', drag and drop a 2 MB weekly church bulletin PDF containing service times and pastor bio, and click 'Read files'. | E12: Server parses PDF text streams, applies NLP regex patterns, extracts service times and staff items, and displays quotes referencing PDF filename. | G12: Unknown
A13: Ingest church flyer image via Vision AI OCR | B13: Multimodal Vision Extraction | C13: Builder | D13: Upload church flyer image (JPEG/PNG) displaying worship schedule and logo. | E13: Vision AI transcribes image text into machine-readable prose; rules parser extracts church schedule and logo reference. | G13: Unknown
... A21: Publish live production church without invite code | B21: Tenant Provisioning Guardrail | C21: Builder | D21: On preview screen, attempt to provision and deploy a new live church tenant without entering an invite code. | E21: System provisions new church tenant and deploys public domain. | G21: Unknown

Sheet Home
A1: Name of Test Case | B1: Category | C1: Name of Page | D1: Action to Take | E1: Expected Outcome | F1: Outcome/Result | G1: Pass/Fail
A2: Hero CTA: Find a place to serve button | B2: Navigation & User Flow | C2: Home | D2: Click 'Find a place to serve' primary button on the hero banner. | E2: Application navigates directly to '#/serve/find' volunteer matching page. | G2: Unknown
A3: Hero CTA: Planning your first visit button | B3: Navigation & User Flow | C3: Home | D3: Click 'Planning your first visit?' secondary button on the hero banner. | E3: Application navigates directly to '#/guests/plan' first-time guest page. | G3: Unknown
A4: Hero CTA: Ask Tekton chat launcher | B4: AI Assistant Integration | C4: Home | D4: Click 'Ask Tekton' button with chat icon in the hero banner. | E4: Sitewide chat assistant drawer slides open from right with greeting message. | G4: Unknown
A5: Serve feature card navigation | B5: Feature Card Routing | C5: Home | D5: Click 'Serve' feature card in the main features grid. | E5: Navigates to '#/serve' ministries directory overview page. | G5: Unknown
A6: Sermon Notes feature card navigation | B6: Feature Card Routing | C6: Home | D6: Click 'Sermon Notes' feature card in the main features grid. | E6: Navigates to '#/notes' sermon notes transcript archive. | G6: Unknown
A7: Give feature card goal progress bar display | B7: Fundraising Goal Tracking | C7: Home | D7: Inspect Give feature card when a church fund has an active fundraising goal. | E7: Card displays fund name, raised amount, goal amount, and accurately styled visual percentage progress bar. | G7: Unknown
A8: Get to know us directory quick button | B8: Quick Links Navigation | C8: Home | D8: Click 'Contact directory' button in the 'Get to know us' section. | E8: Navigates directly to '#/about/directory' staff contact listing. | G8: Unknown
A9: Service times and address card rendering | B9: Visitor Information | C9: Home | D9: Inspect 'Service times' block on the Home page. | E9: Displays weekly gathering schedule (e.g. 'Sunday 9:00 AM & 11:00 AM') and church physical address with location pin icon. | G9: Unknown
A10: Watch Live external link when livestream is unconfigured | B10: Livestream Integration | C10: Home | D10: Click 'Watch live' hero action button when church has no active livestream URL configured. | E10: Displays friendly popup indicating no active broadcast is currently streaming. | G10: Unknown
A11: Hero about text rendering on new unconfigured church | B11: Tenant Onboarding Display | C11: Home | D11: Open Home page for newly provisioned church with no about description provided. | E11: Displays elegant onboarding prompt guiding visitors and staff to add story. | G11: Unknown

Sheet Plan Your Visit
A1: Name of Test Case | B1: Category | C1: Name of Page | D1: Action to Take | E1: Expected Outcome | F1: Outcome/Result | G1: Pass/Fail
A2: Submit guest visit RSVP registration form | B2: Guest Registration Flow | C2: Guests - Plan Your Visit | D2: Fill in name 'Sarah Jenkins', contact 'sarah@example.org', select 'Sunday 9:00 AM', party size 3, and click 'Let us know you’re coming'. | E2: Form submits to POST /api/visits, receives visit token, saves token to localStorage, and updates UI to registered state. | G2: Unknown
A3: Validate required fields in visit registration | B3: Form Validation | C3: Guests - Plan Your Visit | D3: Leave name and contact fields blank and click 'Let us know you’re coming'. | E3: Browser displays HTML5 validation prompt on required name and contact inputs; submission is halted. | G3: Unknown
A4: Select service time from dynamic dropdown | B4: Form Interaction | C4: Guests - Plan Your Visit | D4: Click service time dropdown and select second gathering 'Sunday 11:00 AM'. | E4: Selected service time state updates and is included in the visit payload. | G4: Unknown
A5: Toggle 'I’d like someone to meet me' host checkbox | B5: Hospitality Preferences | C5: Guests - Plan Your Visit | D5: Uncheck the 'I’d like someone to meet me at the front doors' checkbox. | E5: wantsHost state sets to false; submitted visit payload reflects 'wants_host: false'. | G5: Unknown
A6: Click 'I’m on my way' arrival notification button | B6: Guest Arrival Flow | C6: Guests - Plan Your Visit | D6: On the confirmed visit card, click 'I’m on my way' button. | E6: Visits API updates status to 'on_the_way'; welcome team queue receives live status update. | G6: Unknown
A7: Click 'I have arrived' check-in button | B7: Guest Arrival Flow | C7: Guests - Plan Your Visit | D7: On confirmed visit card, click 'I have arrived' button. | E7: Visits API updates status to 'arrived'; triggers desktop notification on welcome team workstation. | G7: Unknown
A8: Expand FAQ accordion to read answer | B8: Content Disclosure | C8: Guests - Plan Your Visit | D8: Click on question 'What should I wear?' in the FAQ section. | E8: Accordion item expands revealing helpful answer about casual attire. | G8: Unknown
A9: Open Google Maps directions link | B9: External Navigation | C9: Guests - Plan Your Visit | D9: Click 'Get directions' button next to the church address. | E9: Opens Google Maps search query with church street address in new browser tab. | G9: Unknown
A10: Interactive parking spot selection on mobile Safari touchscreens | B10: Touchscreen Mapping | C10: Guests - Plan Your Visit | D10: Tap parking spot on campus SVG map using an iOS Safari mobile browser. | E10: Spot highlights and selection binds to form payload. | G10: Unknown
A11: Guest RSVP submission with international phone number format | B11: Input Sanitization & Regex | C11: Guests - Plan Your Visit | D11: Enter international format contact number '+44 20 7946 0958' in RSVP contact field. | E11: Validates international phone format and registers visit. | G11: Unknown

Sheet Welcome Team
A1: Name of Test Case | B1: Category | C1: Name of Page | D1: Action to Take | E1: Expected Outcome | F1: Outcome/Result | G1: Pass/Fail
A2: Block unauthorized visitor access to welcome queue | B2: Access Control | C2: Guests - Welcome Team | D2: Navigate to '#/guests/welcome' as an unauthenticated public visitor. | E2: Welcome queue is hidden; displays 'StaffOnly' notice prompting staff sign-in. | G2: Unknown
A3: Display arrived guests queue for signed-in staff | B3: Queue Visibility | C3: Guests - Welcome Team | D3: Sign in as staff and open '#/guests/welcome'. | E3: Displays WelcomeQueue component showing waiting list and planned guests list. | G3: Unknown
A4: Persist host staff name in local storage | B4: Host Identity | C4: Guests - Welcome Team | D4: Type host name 'Brother David' into 'Your name' field and reload page. | E4: Host name 'Brother David' is saved to localStorage and restored on reload. | G4: Unknown
A5: Claim an arrived guest from waiting queue | B5: Host Assignment | C5: Guests - Welcome Team | D5: Click 'I’ll meet them' button on a waiting guest card. | E5: Calls POST /visits/:id/claim with hostName; marks guest as claimed by Brother David. | G5: Unknown
A6: Dismiss welcomed guest from queue | B6: Status Lifecycle | C6: Guests - Welcome Team | D6: Click 'Welcomed' checkmark button on a claimed guest card. | E6: Calls PATCH /visits/:id with status 'welcomed'; removes guest from active waiting list. | G6: Unknown
A7: Display accurate party size and host preference tags | B7: Metadata Rendering | C7: Guests - Welcome Team | D7: Inspect waiting guest card for party of 4 who prefers not to be met. | E7: Card displays 'Party of 4' badge and muted notice 'Prefers not to be met at door'. | G7: Unknown
A8: Display elapsed waiting time counter | B8: Queue Metrics | C8: Guests - Welcome Team | D8: Observe waiting guest card for guest who arrived 6 minutes ago. | E8: Displays elapsed waiting counter 'Arrived 6m ago' updating periodically. | G8: Unknown
A9: Real-time queue polling updates without refresh | B9: Real-time Synchronization | C9: Guests - Welcome Team | D9: Keep Welcome Team screen open while a new guest checks in on another device. | E9: Background 5-second interval poll detects new arrival and adds card to queue with arrival chime/alert. | G9: Unknown
A10: Browser arrival push notifications on mobile browsers (iOS / Android) | B10: Web Push Notifications | C10: Guests - Welcome Team | D10: Tap 'Enable arrival notifications' on iOS Safari or mobile web browser. | E10: Native browser arrival push notifications fire when guest arrives. | G10: Unknown
A11: Concurrent guest claim race condition between two hosts | B11: Concurrency & Locking | C11: Guests - Welcome Team | D11: Two welcome hosts click 'I’ll meet them' on the same arrived guest card within 1 second. | E11: Optimistic concurrency lock notifies second host that guest was already claimed by another team member. | G11: Unknown

Sheet Serve
A1: Name of Test Case | B1: Category | C1: Name of Page | D1: Action to Take | E1: Expected Outcome | F1: Outcome/Result | G1: Pass/Fail
A2: Filter serving teams by keyword search | B2: Search & Filtering | C2: Serve | D2: Type 'worship' into ministry search input field. | E2: List filters instantly to ministries containing 'worship' in name, description, or category. | G2: Unknown
A3: Toggle 'Urgent needs only' filter checkbox | B3: Urgency Triage | C3: Serve | D3: Click 'Urgent needs only' filter button. | E3: Displays only ministries where unfilled volunteer slots are 35% or higher, with urgent badge. | G3: Unknown
A4: Expand ministry card to inspect team leader and roles | B4: Detail Disclosure | C4: Serve | D4: Click on 'Kids Ministry' card in the serving grid. | E4: Detailed drawer opens showing team description, time commitments, and ministry leader contact. | G4: Unknown
A5: Bookmark recommended ministry to saved shortlist | B5: Shortlist Management | C5: Serve | D5: Click 'Save to shortlist' bookmark icon on 'Worship Collective' recommendation card. | E5: Ministry is added to local saved list; navigation badge count increments by 1. | G5: Unknown
A6: View saved ministries tab | B6: Shortlist Review | C6: Serve | D6: Click 'Saved' sub-navigation tab ('#/serve/saved'). | E6: Displays all bookmarked serving opportunities with option to submit interest request. | G6: Unknown
A7: Staff view of filed volunteer connection requests | B7: Staff Queue Management | C7: Serve | D7: Sign in as staff and open '#/serve/saved' requests queue. | E7: Staff sees full list of member-submitted volunteer inquiries and chat connection requests. | G7: Unknown
A8: Staff approves volunteer connection request | B8: Workflow State Change | C8: Serve | D8: Click 'Connect' checkmark button on a pending volunteer request. | E8: Calls PATCH /requests/:id with status 'connected'; moves request to active connections list. | G8: Unknown
A9: Staff archives or deletes processed request | B9: Queue Cleanup | C9: Serve | D9: Click 'Remove' trash icon on an archived volunteer request. | E9: Calls DELETE /requests/:id; removes request card from staff queue view. | G9: Unknown
A10: AI volunteer matching with single-word generic input | B10: AI Recommendation Bounds | C10: Serve | D10: On volunteer finder, enter single word 'anything' into gifts input and click 'Find matching places'. | E10: Prompts user to specify gifts/skills or provides general serving opportunities. | G10: Unknown
A11: Real-time staff queue update across multiple browser sessions | B11: Cross-client Synchronization | C11: Serve | D11: Visitor files a volunteer request in chat; observe staff queue on a separate un-refreshed staff browser. | E11: Staff queue updates automatically via WebSocket or background push without manual reload. | G11: Unknown

Sheet Sermon Notes
A1: Name of Test Case | B1: Category | C1: Name of Page | D1: Action to Take | E1: Expected Outcome | F1: Outcome/Result | G1: Pass/Fail
A2: Browse sermon catalog and open message | B2: Content Discovery | C2: Sermon Notes | D2: Click on sermon card 'The Heart of the Father - Luke 15' in sermon list. | E2: Navigates to '#/notes/:id'; loads full sermon transcript, media player, and AI ask panel. | G2: Unknown
A3: Ask AI question about sermon content | B3: AI Sermon Q&A | C3: Sermon Notes | D3: In sermon ask box, type 'What did the pastor say about the older brother?' and click Ask. | E3: AI queries sermon embeddings, returns answer summarizing pastor's points, and quotes verbatim sentences with timestamps. | G3: Unknown
A4: Click transcript timestamp to seek media player | B4: Media Synchronization | C4: Sermon Notes | D4: Click timestamp link '[14:32]' inside sermon transcript text. | E4: Audio/video player seeks immediately to 14 minutes 32 seconds and starts playback. | G4: Unknown
A5: Toggle 'Bible quotes' highlight filter | B5: Transcript Annotation | C5: Sermon Notes | D5: Click 'Bible quotes' button in highlight categories toggle bar. | E5: All direct Scripture quotations in transcript highlight with gold background styling. | G5: Unknown
A6: Tap scripture highlight to open YouVersion verse card | B6: Scripture Integration | C6: Sermon Notes | D6: Click highlighted Bible reference 'Romans 8:28' in sermon transcript. | E6: VerseCard popover opens displaying full text of Romans 8:28 fetched from Bible API. | G6: Unknown
A7: Switch preferred Bible translation in reader preferences | B7: User Preferences | C7: Sermon Notes | D7: Open reader settings and change translation from NIV to ESV. | E7: Passage references reload with English Standard Version text; preference saved to localStorage. | G7: Unknown
A8: Adjust transcript font size for accessibility | B8: Accessibility & Display | C8: Sermon Notes | D8: Click font size '+' button in reader toolbar. | E8: Transcript body text size increases from 16px to 19px for enhanced readability. | G8: Unknown
A9: Staff creates new sermon note via YouTube URL | B9: Media Ingestion - YouTube | C9: Sermon Notes | D9: Sign in as staff, click '+ New note', enter valid YouTube link, title 'Sunday Service', and click 'Create note'. | E9: Backend queues YouTube audio download and Whisper transcription job; sermon status becomes 'queued'. | G9: Unknown
A10: Process sermon video with bot-protected YouTube URL | B10: Media Ingestion - YouTube | C10: Sermon Notes | D10: Submit a YouTube sermon URL that requires bot challenge or sign-in verification. | E10: System bypasses bot challenge and downloads audio for transcription. | G10: Unknown
A11: Upload video file exceeding 95 MB limit | B11: File Upload Validation | C11: Sermon Notes | D11: Attach 120 MB MP4 sermon recording and click 'Create note'. | E11: Client-side file validation prevents upload and shows clear file size guidance. | G11: Unknown

Sheet Calendar
A1: Name of Test Case | B1: Category | C1: Name of Page | D1: Action to Take | E1: Expected Outcome | F1: Outcome/Result | G1: Pass/Fail
A2: Toggle between monthly calendar grid and upcoming list view | B2: View Mode Switching | C2: Calendar | D2: Click 'List view' button in the calendar toolbar. | E2: Display changes from 7-day monthly grid to chronological list view grouped by date. | G2: Unknown
A3: Filter calendar events by category | B3: Category Filtering | C3: Calendar | D3: Click category filter button 'Youth & Kids'. | E3: Calendar highlights/shows only events tagged with 'Youth & Kids' category. | G3: Unknown
A4: Search calendar gatherings by keyword | B4: Keyword Search | C4: Calendar | D4: Type 'prayer' into calendar search bar. | E4: Filters calendar display to events containing 'prayer' in title or description. | G4: Unknown
A5: Navigate across calendar months | B5: Date Navigation | C5: Calendar | D5: Click 'Next month' arrow button in calendar header. | E5: Calendar advances to next month (e.g. November 2026); fetches and displays that month's events. | G5: Unknown
A6: Inspect event detail modal by clicking calendar cell | B6: Event Inspection | C6: Calendar | D6: Click on 'Community Outreach Day' event entry in the grid. | E6: Event detail modal opens showing date, time, location, host ministry, and full event description. | G6: Unknown
A7: Staff opens '+ Add event' modal and creates new event | B7: Event Creation | C7: Calendar | D7: Sign in as staff, click '+ Add event', fill in title 'Church Picnic', date, time, location, and click Save. | E7: Calls POST /events with event JSON; returns created event; reloads calendar with new item visible. | G7: Unknown
A8: Validate required fields in event creation form | B8: Form Validation | C8: Calendar | D8: In '+ Add event' modal, leave title empty and click Save. | E8: Form validation halts submission; highlights empty title field with required error. | G8: Unknown
A9: Staff deletes or cancels scheduled event | B9: Event Deletion | C9: Calendar | D9: Open event detail modal as staff and click 'Delete event' button with confirmation. | E9: Calls DELETE /events/:id; event is removed from calendar display. | G9: Unknown
A10: Automatic AI bulletin summary generation on event creation | B10: AI Content Generation | C10: Calendar | D10: As staff, create a new calendar event and check for automated AI bulletin summary. | E10: AI endpoint generates welcoming 2-sentence bulletin summary. | G10: Unknown
A11: Export calendar gatherings to Apple iCal / .ics file | B11: Calendar Standards Export | C11: Calendar | D11: Click 'Add to calendar' / export button on an event detail view. | E11: Downloads standardized .ics file for importing into Apple Calendar or Outlook. | G11: Unknown

Sheet Give
A1: Name of Test Case | B1: Category | C1: Name of Page | D1: Action to Take | E1: Expected Outcome | F1: Outcome/Result | G1: Pass/Fail
A2: Select preset donation amount button | B2: Donation Flow | C2: Give | D2: Click preset dollar amount button '$100'. | E2: Donation total updates to '$100.00' and highlights the $100 button. | G2: Unknown
A3: Enter custom donation dollar amount with validation | B3: Form Validation | C3: Give | D3: Click 'Custom amount' input, type '150.00', and proceed. | E3: Custom amount input accepts numeric value and sets donation total to $150.00. | G3: Unknown
A4: Select designated fund from fund selector dropdown | B4: Fund Allocation | C4: Give | D4: Open fund selector dropdown and choose 'Missions Fund'. | E4: Donation allocation updates to 'Missions Fund'; fund ID included in checkout session request. | G4: Unknown
A5: Browse active mission trips on Mission Trips tab | B5: Mission Trips Discovery | C5: Give | D5: Click 'Mission trips' tab ('#/give/trips'). | E5: Displays active mission trips with destination, trip dates, team size, and funding progress bar. | G5: Unknown
A6: Click 'Support this trip' to prefill donation fund | B6: Designated Trip Support | C6: Give | D6: Click 'Support this trip' button on Guatemala outreach card. | E6: Navigates to '#/give' with Guatemala mission fund pre-selected in fund dropdown. | G6: Unknown
A7: Submit volunteer application to join a mission trip | B7: Trip Volunteer Application | C7: Give | D7: Click 'Apply to go', fill in applicant name, email, skills, and submit application. | E7: Calls POST /trips/:id/apply; submits application for staff review; displays confirmation. | G7: Unknown
A8: Access monthly recurring gift management via secure token | B8: Subscription Self-Service | C8: Give | D8: Open manage gift link with valid token ('#/give/manage/:church.:token'). | E8: Loads donor's monthly gift details: amount, designated fund, next billing date, and cancellation action. | G8: Unknown
A9: Cancel recurring monthly donation | B9: Subscription Management | C9: Give | D9: On the manage recurring gift screen, click 'Cancel monthly gift' and confirm in prompt. | E9: Calls DELETE /giving/recurring; cancels Stripe subscription; displays cancellation confirmation. | G9: Unknown
A10: Direct credit card donation processing in Demo Mode | B10: Payment Processing | C10: Give | D10: Enter donation amount and attempt live credit card payment on demo church ('slug: demo'). | E10: Processes live donation via Stripe payment gateway. | G10: Unknown
A11: Monthly recurring donation setup without Stripe Connect | B11: Payment Configuration Prerequisite | C11: Give | D11: Attempt to set up monthly recurring donation on a church that has not connected Stripe. | E11: Monthly recurring option is disabled with clear prerequisite explanation. | G11: Unknown

Sheet Prayer Map
A1: Name of Test Case | B1: Category | C1: Name of Page | D1: Action to Take | E1: Expected Outcome | F1: Outcome/Result | G1: Pass/Fail
A2: Render interactive Leaflet world map with partner borders | B2: Map Visualization | C2: Prayer Map | D2: Navigate to '#/prayer'. | E2: Leaflet map initializes centered on global partner regions with highlighted country border polygons. | G2: Unknown
A3: Click country prayer beacon to inspect prayer focus | B3: Prayer Focus Inspection | C3: Prayer Map | D3: Click pulsing prayer beacon pin located on country 'Nepal'. | E3: Map centers on Nepal; 'prayer-detail' card below map populates with Nepal prayer needs and cultural context. | G3: Unknown
A4: Click real news pin to inspect verified headline and date | B4: News Pin Popup | C4: Prayer Map | D4: Click on red news pin marker located in Kenya. | E4: Popup appears displaying verified news headline, publication date, and summary. | G4: Unknown
A5: Verify sensitive nation security safeguard hides team coordinates | B5: Security & Anonymization | C5: Prayer Map | D5: Inspect prayer beacon for restricted/sensitive country. | E5: Pulsing beacon displays only country-level centroid; no local address, GPS coordinates, or missionary names are exposed. | G5: Unknown
A6: Verify compact labels toggle on dense zoom levels | B6: Label Collision Prevention | C6: Prayer Map | D6: Zoom out map to world overview level. | E6: LabelDensity hook detects potential label collisions and adds 'compact-labels' class to suppress overlapping text. | G6: Unknown
A7: Click 'Fit to borders' to re-center partner nations | B7: Map Bounds Ergonomics | C7: Prayer Map | D7: Pan map far off-center and refresh or trigger fit bounds. | E7: Map automatically calculates bounding box of all church mission regions and fits view with 40px padding. | G7: Unknown
A8: Filter prayer updates by selected country | B8: Geographic Filtering | C8: Prayer Map | D8: Select country 'Colombia' from partner nations list. | E8: News and prayer requests list below map filters exclusively to items matching Colombia country code. | G8: Unknown
A9: Smooth scroll to selected prayer detail card | B9: Interaction Ergonomics | C9: Prayer Map | D9: Click any country beacon on desktop viewport. | E9: Browser smoothly scrolls down to position 'prayer-detail' card into prominent view. | G9: Unknown
A10: Map rendering during backend API service outage | B10: Fault Resilience | C10: Prayer Map | D10: Disconnect backend API server and navigate to '#/prayer'. | E10: Map displays cached offline regions with retry option. | G10: Unknown
A11: Country beacon precision on small island nations | B11: Geographic Centroid Precision | C11: Prayer Map | D11: Inspect prayer beacon for small archipelagic partner nation (e.g. Fiji). | E11: Beacon pins directly to inhabited land territory. | G11: Unknown

Sheet About - Our Story
A1: Name of Test Case | B1: Category | C1: Name of Page | D1: Action to Take | E1: Expected Outcome | F1: Outcome/Result | G1: Pass/Fail
A2: Display church mission statement banner | B2: Mission Display | C2: About - Our Story | D2: Navigate to '#/about'. | E2: Displays 'Our mission' card featuring the church's core mission statement in prominent typography. | G2: Unknown
A3: Render church narrative story and history paragraphs | B3: Storytelling Content | C3: About - Our Story | D3: Inspect 'Our story' section on About page. | E3: Renders formatted narrative paragraphs detailing church founding, vision, and community impact. | G3: Unknown
A4: Inspect core values cards with distinct icons | B4: Core Values | C4: About - Our Story | D4: Inspect 'What we value' grid on About page. | E4: Displays core value cards (e.g. Grace, Community, Service, Scripture) each with distinct icon and description. | G4: Unknown
A5: Verify office hours and physical location in visit block | B5: Facility Details | C5: About - Our Story | D5: Inspect 'Find us / Come visit' section on About page. | E5: Displays church street address, office hours, and weekly gathering times. | G5: Unknown
A6: Click 'Plan your visit' CTA button | B6: Internal Navigation | C6: About - Our Story | D6: Click 'Plan your visit' primary button at bottom of story page. | E6: Navigates directly to '#/guests/plan' guest visit registration page. | G6: Unknown
A7: Click 'What we believe' button to navigate to beliefs tab | B7: Sub-navigation | C7: About - Our Story | D7: Click 'What we believe' secondary button. | E7: Navigates to '#/about/beliefs' statement of faith tab. | G7: Unknown
A8: Click 'Connect with us' button to navigate to connect tab | B8: Sub-navigation | C8: About - Our Story | D8: Click 'Connect with us' button. | E8: Navigates to '#/about/connect' next steps page. | G8: Unknown
A9: Hover sourced story text to verify import quote attribution | B9: Provenance Verification | C9: About - Our Story | D9: When previewing an imported church site, hover over imported About text. | E9: Sourced component tooltip appears displaying source URL and verbatim quote from imported website. | G9: Unknown
A10: Verify dynamic church name replacement across all story text | B10: Tenant Personalization | C10: About - Our Story | D10: View About page across two different tenant church configurations. | E10: Intro subtitle and story text dynamically replace placeholder with active church name. | G10: Unknown
A11: Provenance quote tooltip on mobile touchscreens | B11: Touchscreen Tooltip Ergonomics | C11: About - Our Story | D11: Tap sourced sentence on mobile phone to inspect provenance source and quote. | E11: Mobile modal or popover opens displaying quote attribution. | G11: Unknown

Sheet About - Beliefs
A1: Name of Test Case | B1: Category | C1: Name of Page | D1: Action to Take | E1: Expected Outcome | F1: Outcome/Result | G1: Pass/Fail
A2: Render statement of belief introductory preamble | B2: Doctrinal Overview | C2: About - Beliefs | D2: Navigate to '#/about/beliefs'. | E2: Displays preamble card: 'What we hold to' explaining the convictions that shape teaching and life together. | G2: Unknown
A3: Verify sequential two-digit numbering on belief articles | B3: Article Enumeration | C3: About - Beliefs | D3: Inspect numbered belief badges in the beliefs list. | E3: Belief items display clean two-digit index badges: '01', '02', '03' etc. | G3: Unknown
A4: Inspect Article 01 on Scripture and Inspiration | B4: Theological Content | C4: About - Beliefs | D4: Inspect belief item 01 'The Bible'. | E4: Displays doctrine affirming the authority, inspiration, and trustworthiness of the Scriptures. | G4: Unknown
A5: Inspect Article 02 on God and the Trinity | B5: Theological Content | C5: About - Beliefs | D5: Inspect belief item 02 'God'. | E5: Displays doctrine on God as Creator and eternally existing in three persons: Father, Son, and Holy Spirit. | G5: Unknown
A6: Inspect Article on Salvation by Grace through Faith | B6: Theological Content | C6: About - Beliefs | D6: Inspect belief item on 'Salvation'. | E6: Displays doctrine explaining salvation as a free gift received through faith in Jesus Christ alone. | G6: Unknown
A7: Render custom imported beliefs statement for imported site | B7: Custom Tenant Content | C7: About - Beliefs | D7: Open Beliefs page on church where Tekton imported custom doctrinal statement. | E7: ChurchBeliefs component renders the church's own imported doctrinal articles instead of sample data. | G7: Unknown
A8: Display demo church statement of faith fallback | B8: Demo Data Integrity | C8: About - Beliefs | D8: Open Beliefs page while viewing demo church tenant. | E8: Renders verified default beliefs dataset from data/beliefs.json. | G8: Unknown
A9: Sub-navigation tab switching to Our Story and Directory | B9: Sub-navigation | C9: About - Beliefs | D9: Click 'Our story' tab in sub-navigation bar. | E9: Switches view seamlessly back to '#/about' with active tab state updating. | G9: Unknown
A10: Semantic ordered list accessibility check (<ol>, <li>) | B10: Accessibility Standards | C10: About - Beliefs | D10: Inspect DOM structure of the beliefs listing. | E10: Belief items are structured inside semantic <ol class='beliefs'> and <li class='card belief'> elements for screen readers. | G10: Unknown
A11: Doctrinal beliefs display on imported site without statement of faith | B11: Conditional Routing | C11: About - Beliefs | D11: Open '#/about/beliefs' on church imported from a website with no beliefs page. | E11: Displays friendly notice explaining church has not published doctrinal beliefs. | G11: Unknown

Sheet About - News
A1: Name of Test Case | B1: Category | C1: Name of Page | D1: Action to Take | E1: Expected Outcome | F1: Outcome/Result | G1: Pass/Fail
A2: Filter news feed by kind: Updates vs Articles | B2: Content Filtering | C2: About - News | D2: Click 'Updates' filter toggle button. | E2: News feed filters to display only short announcement updates; longer articles are hidden. | G2: Unknown
A3: Filter news posts by category tag pill | B3: Taxonomy Filtering | C3: About - News | D3: Click category pill 'Outreach' in tag suggestions bar. | E3: Displays only posts tagged with the 'Outreach' category. | G3: Unknown
A4: Expand long-form article to read full text | B4: Content Disclosure | C4: About - News | D4: Click 'Read the full article' button on an article exceeding 420 characters. | E4: Article expands smoothly revealing full body paragraphs and hides the expand button. | G4: Unknown
A5: Verify AI 3-bullet summary on featured articles | B5: AI Article Summarization | C5: About - News | D5: Inspect header of a featured pastor article. | E5: Displays AI bullet summary section containing 3 concise takeaway bullet points. | G5: Unknown
A6: Click internal action link on quick update post | B6: Contextual Action Links | C6: About - News | D6: Click 'Find a place to serve' button on volunteer announcement update. | E6: Executes in-app routing to '#/serve/find' without triggering full page reload. | G6: Unknown
A7: Open external reference link in new browser tab | B7: External Link Handling | C7: About - News | D7: Click 'Learn more' external web link on community partner update. | E7: Opens external URL in a new browser tab with rel='noopener noreferrer'. | G7: Unknown
A8: Staff opens 'Write a post' modal and creates new article | B8: Post Creation | C8: About - News | D8: Sign in as staff, click '+ Write a post', enter title 'Fall Outreach Kickoff', select kind 'article', write body, and click Publish. | E8: Calls POST /blog; article is saved and immediately appears at the top of the news feed. | G8: Unknown
A9: Staff deletes outdated announcement post | B9: Content Moderation | C9: About - News | D9: Click 'Delete post' trash button on an expired announcement as staff. | E9: Calls DELETE /blog/:id; post is removed from news listing. | G9: Unknown
A10: Article AI summary generation on non-standard formatting | B10: AI Summary Robustness | C10: About - News | D10: Staff publishes an article containing unusual ASCII formatting or markdown bullet lists. | E10: AI summarizes article into 3 clean bullet points. | G10: Unknown
A11: Pagination / infinite scroll on large archive of news posts | B11: Performance & Data Scalability | C11: About - News | D11: Scroll to bottom of news feed containing 50+ published posts. | E11: Pagination or infinite scroll loads older posts in manageable batches. | G11: Unknown

Sheet About - Directory
A1: Name of Test Case | B1: Category | C1: Name of Page | D1: Action to Take | E1: Expected Outcome | F1: Outcome/Result | G1: Pass/Fail
A2: Search directory by pastor or leader name | B2: Directory Search | C2: About - Directory | D2: Type 'Marcus' into directory search input. | E2: Staff list filters immediately to staff cards matching 'Marcus'. | G2: Unknown
A3: Search directory by ministry or department role | B3: Role Filtering | C3: About - Directory | D3: Type 'worship' into directory search input. | E3: Filters directory to staff members and ministry leaders whose role or bio contains 'worship'. | G3: Unknown
A4: Click staff email address to open email client | B4: Click-to-Email | C4: About - Directory | D4: Click on pastor email link 'pastor@example.org'. | E4: Link triggers mailto:pastor@example.org opening default email client. | G4: Unknown
A5: Verify Church Office card address and office hours | B5: Facility Details | C5: About - Directory | D5: Inspect top 'Church office' block on Directory page. | E5: Displays church physical street address, phone, email, and weekly office hours. | G5: Unknown
A6: Inspect pastor biography and role card | B6: Personnel Profile | C6: About - Directory | D6: Inspect card for Senior Pastor. | E6: Card displays pastor name, official role title, bio summary, and direct email link. | G6: Unknown
A7: Verify imported staff provenance source attribution tooltip | B7: Provenance Verification | C7: About - Directory | D7: Hover over pastor name on an imported church preview site. | E7: Sourced tooltip appears citing source page (e.g. '/our-team.html') and exact quote from original site. | G7: Unknown
A8: Display ministry leaders associated with respective teams | B8: Ministry Leadership | C8: About - Directory | D8: Scroll to 'Ministry leaders' section in directory. | E8: Displays cards for leaders heading specific ministries (e.g. 'Leads Kids Ministry'). | G8: Unknown
A9: Clear search input to restore full staff directory listing | B9: Filter Reset | C9: About - Directory | D9: Clear text from search input box. | E9: Directory instantly restores full listing of all pastors, staff, and ministry leads. | G9: Unknown
A10: Verify empty state message on unmatched search query | B10: Empty State Handling | C10: About - Directory | D10: Type non-existent name 'Zyxwvut' into directory search box. | E10: Directory sections hide and show zero-match empty state without crashing. | G10: Unknown
A11: Phone number click-to-call on desktop browser without telephony app | B11: Desktop Protocol Handling | C11: About - Directory | D11: Click church phone link on desktop browser with no VoIP/telephone app configured. | E11: Displays prompt to copy phone number to clipboard. | G11: Unknown

Sheet About - Connect
A1: Name of Test Case | B1: Category | C1: Name of Page | D1: Action to Take | E1: Expected Outcome | F1: Outcome/Result | G1: Pass/Fail
A2: Click 'Visiting for the first time' pathway card | B2: Pathway Navigation | C2: About - Connect | D2: Click 'Visiting for the first time' feature card. | E2: Navigates directly to '#/guests/plan' first-time visitor page. | G2: Unknown
A3: Click 'Find a place to serve' pathway card | B3: Pathway Navigation | C3: About - Connect | D3: Click 'Find a place to serve' feature card. | E3: Navigates directly to '#/serve/find' volunteer matching page. | G3: Unknown
A4: Click 'Come to an event' pathway card | B4: Pathway Navigation | C4: About - Connect | D4: Click 'Come to an event' feature card. | E4: Navigates directly to '#/calendar' calendar gatherings page. | G4: Unknown
A5: Browse community small groups listing | B5: Community Groups | C5: About - Connect | D5: Inspect 'Groups / Find your people' section on Connect page. | E5: Displays active small groups with group name, meeting schedule ('Tuesdays 7pm'), location, and target audience. | G5: Unknown
A6: Click external registration link for imported form | B6: External Form Integration | C6: About - Connect | D6: Click on imported sign-up form link (e.g. Church Center / Google Forms). | E6: Opens external registration form in a new browser tab with rel='noopener noreferrer'. | G6: Unknown
A7: Fill connect inquiry form and select interest topic | B7: Lead Capture | C7: About - Connect | D7: Fill in name 'James Carter', contact 'james@example.org', select interest 'Small groups', type note, and inspect mailto button. | E7: Form updates mailto link with encoded subject 'Connecting with Grace Church: Small groups' and body text. | G7: Unknown
A8: Validate connect form requires name and church contact email | B8: Form Validation | C8: About - Connect | D8: Leave name input blank and inspect 'Send message' button state. | E8: 'Send message' button is disabled until a name is entered and church email exists. | G8: Unknown
A9: Click 'Ask Tekton' quick link to open sitewide chat modal | B9: Assistant Hand-off | C9: About - Connect | D9: Click 'Ask Tekton' secondary button inside connect block. | E9: Opens sitewide chat assistant drawer for immediate interactive conversation. | G9: Unknown
A10: Submit connect inquiry expecting server inbox storage | B10: Lead Capture Storage | C10: About - Connect | D10: Fill out connect form and click 'Send message' expecting submission to church database. | E10: Submits lead to backend CRM/inbox database. | G10: Unknown
A11: Inquiry submission when church contact email is unconfigured | B11: Form Validation & Fallback | C11: About - Connect | D11: Attempt to submit connect form on church where email is unlisted. | E11: Form provides alternative contact method or stores lead in database. | G11: Unknown

Sheet Admin - Staff
A1: Name of Test Case | B1: Category | C1: Name of Page | D1: Action to Take | E1: Expected Outcome | F1: Outcome/Result | G1: Pass/Fail
A2: Staff authentication with valid email and password | B2: Staff Authentication | C2: Admin - Church Staff | D2: Navigate to '#/staff', enter staff email 'admin@example.org', staff password, and click 'Sign in'. | E2: Calls /admin/login endpoint, receives verified session token, stores token, and renders Staff Dashboard. | G2: Unknown
A3: Display error banner on invalid login credentials | B3: Authentication Error Handling | C3: Admin - Church Staff | D3: Enter wrong password and click 'Sign in'. | E3: Form remains on screen; displays error banner 'Invalid password. Please check and try again.' | G3: Unknown
A4: Connect Stripe account button redirection | B4: Stripe Onboarding | C4: Admin - Church Staff | D4: On Overview tab, click 'Connect Stripe' onboarding button. | E4: Calls /admin/stripe/connect endpoint and redirects to Stripe Connect OAuth flow. | G4: Unknown
A5: Create a new church fund with fundraising dollar goal | B5: Fund Management | C5: Admin - Church Staff | D5: On 'Funds & trips' tab, click '+ Add fund', enter name 'Roof Repair', goal '15000', and click Save. | E5: Calls POST /admin/funds; adds new fund to active funds list and makes available on Give page. | G5: Unknown
A6: Create a new mission trip with dates and target budget | B6: Mission Trip Creation | C6: Admin - Church Staff | D6: Click '+ Add trip', enter destination 'Honduras', departure date, return date, cost '$1,800', and submit. | E6: Calls POST /admin/trips; creates mission trip entity; publishes card on '#/give/trips'. | G6: Unknown
A7: Review and approve volunteer mission trip application | B7: Application Review | C7: Admin - Church Staff | D7: On 'Applications' tab, click 'Approve' on applicant 'David Lee' for Honduras trip. | E7: Calls PATCH /admin/applications/:id with status 'approved'; updates applicant badge to Approved. | G7: Unknown
A8: View confidential donor gifts ledger table | B8: Gifts Ledger | C8: Admin - Church Staff | D8: Click 'Gifts' tab in staff dashboard navigation. | E8: Renders secure gifts table showing donor names, emails, funds, amounts, timestamps, and Stripe charge IDs. | G8: Unknown
A9: Sign out of staff session and return to visitor view | B9: Session Termination | C9: Admin - Church Staff | D9: Click 'Sign out' button in staff dashboard header. | E9: Calls /admin/logout, purges staff session token from storage, and returns UI to visitor browsing mode. | G9: Unknown
A10: Staff session verification during giving microservice outage | B10: Microservice Dependency | C10: Admin - Church Staff | D10: Sign in as staff when giving service is temporarily unreachable. | E10: Displays cached offline staff view or retry countdown. | G10: Unknown
A11: Invite staff member with duplicate email address | B11: Error Handling | C11: Admin - Church Staff | D11: Invite an email that is already registered as a staff member. | E11: Displays inline error stating user already exists in team. | G11: Unknown

Sheet Admin - Setup
A1: Name of Test Case | B1: Category | C1: Name of Page | D1: Action to Take | E1: Expected Outcome | F1: Outcome/Result | G1: Pass/Fail
A2: Update church display name and city in Church Setup | B2: Branding Settings | C2: Admin - Church Setup | D2: Sign in to '#/setup', change church name to 'Grace Fellowship Church', city to 'Denver, CO', and click 'Save changes'. | E2: Calls PUT /api/church/content with updated details; updates document title and header church name. | G2: Unknown
A3: Update church phone number and primary office email | B3: Contact Info Management | C3: Admin - Church Setup | D3: Change church phone to '(555) 019-3322' and email to 'hello@gracechurch.org', and save. | E3: Updates stored church contact facts; reflected across footer, directory, and contact blocks. | G3: Unknown
A4: Set physical street address and weekly office hours | B4: Facility Details | C4: Admin - Church Setup | D4: Update street address to '500 Mountain View Rd' and office hours to 'Tue-Fri 9am-3pm', and save. | E4: Updates facility details; updates Google Maps directions links sitewide. | G4: Unknown
A5: Add new weekly worship service time slot | B5: Service Times Configuration | C5: Admin - Church Setup | D5: Click '+ Add service time', select day 'Sunday', time '5:00 PM', description 'Evening Worship', and click Save. | E5: Adds service slot to church info services array; visible on Home and Plan Your Visit service dropdowns. | G5: Unknown
A6: Remove outdated worship service time slot | B6: Service Times Configuration | C6: Admin - Church Setup | D6: Click 'Remove' trash button on Wednesday 6:30 PM service slot and save. | E6: Deletes service item from services list; removed from public site schedule. | G6: Unknown
A7: Add new frequently asked question (FAQ) and response | B7: FAQ Management | C7: Admin - Church Setup | D7: Click '+ Add FAQ', enter question 'Is there childcare available?', enter answer 'Yes, for ages 0-5', and save. | E7: Appends FAQ item to church faqs array; renders in accordion on Plan Your Visit page. | G7: Unknown
A8: Create a new serving ministry team with team lead | B8: Ministry Provisioning | C8: Admin - Church Setup | D8: Click '+ Add ministry', enter name 'Hospitality Greeters', lead 'Laura Bailey', category 'Hospitality', and save. | E8: Calls PUT /api/church/content with new ministry item; ministry appears on Serve page. | G8: Unknown
A9: Select partner mission countries for Prayer Map display | B9: Prayer Map Configuration | C9: Admin - Church Setup | D9: Check partner countries 'Brazil', 'Japan', and 'Uganda' in the mission regions multi-select list and save. | E9: Updates supported country codes; Prayer Map highlights selected countries with border overlays. | G9: Unknown
A10: Enforce sign-in prompt when unauthenticated user accesses setup | B10: Access Protection | C10: Admin - Church Setup | D10: Navigate to '#/setup' while signed out. | E10: Setup forms are hidden; displays StaffSignIn form with email and password inputs. | G10: Unknown
A11: Concurrent setup updates overwritten without conflict resolution | B11: Concurrency & Locking | C11: Admin - Church Setup | D11: Two staff administrators edit church service times simultaneously from separate laptops. | E11: System detects concurrent modification and flags conflict. | G11: Unknown

Sheet Sitewide Chat
A1: Name of Test Case | B1: Category | C1: Name of Page | D1: Action to Take | E1: Expected Outcome | F1: Outcome/Result | G1: Pass/Fail
A2: Open chat widget by clicking floating action button | B2: Chat Activation | C2: Sitewide Chat (Ask Tekton) | D2: Click floating 'Ask Tekton' sparkle button in bottom-right corner. | E2: Chat panel slides open smoothly; displays greeting message and quick starter prompts. | G2: Unknown
A3: Click starter prompt 'When are services?' | B3: Quick Starter Prompts | C3: Sitewide Chat (Ask Tekton) | D3: Click prompt pill 'When are services?' above chat input. | E3: Submits query to /chat; assistant replies with accurate Sunday and midweek gathering times. | G3: Unknown
A4: Inquire about upcoming gatherings and events | B4: Gathering Inquiries | C4: Sitewide Chat (Ask Tekton) | D4: Type 'What events are happening this week?' and hit Enter. | E4: Assistant queries calendar data and returns scheduled gatherings with dates and times. | G4: Unknown
A5: Ask volunteer question 'How can I get involved?' | B5: Volunteer Guidance | C5: Sitewide Chat (Ask Tekton) | D5: Type 'How can I get involved in serving?' and send. | E5: Assistant explains serving opportunities and provides interactive suggestion link to Serve page. | G5: Unknown
A6: Click inline chat navigation link to jump to Plan Your Visit | B6: In-Chat Deep Linking | C6: Sitewide Chat (Ask Tekton) | D6: Click assistant's suggested action button 'Plan your visit'. | E6: Chat closes and app navigates directly to '#/guests/plan' with focus on visit form. | G6: Unknown
A7: Submit pastoral prayer request with contact details | B7: Prayer Request Filing | C7: Sitewide Chat (Ask Tekton) | D7: Type 'Please pray for my mother recovering from surgery. My email is mary@example.org' and send. | E7: Assistant detects care request, files connection request via action 'hand_off_to_staff', and confirms request saved. | G7: Unknown
A8: Instant staff queue notification for filed prayer request | B8: Staff Notification Handoff | C8: Sitewide Chat (Ask Tekton) | D8: Observe staff navigation badge immediately after filing prayer request. | E8: onRequestFiled callback fires; staff navigation badge count increments by 1 instantly. | G8: Unknown
A9: Multi-turn conversation context retention | B9: Session Context Retention | C9: Sitewide Chat (Ask Tekton) | D9: Ask 'Where is the church located?' followed by 'Is there parking there?'. | E9: Assistant recalls previous reference to church address and answers parking question in context. | G9: Unknown
A10: Complex theological inquiry when AI service is in demo mode | B10: AI Demo Fallback | C10: Sitewide Chat (Ask Tekton) | D10: Ask chat assistant 'What is the church's view on eschatology and the millennium?' when LLM is unconfigured. | E10: Provides helpful theological overview based on church doctrine. | G10: Unknown
A11: Prayer request filing without valid contact info provided | B11: Input Validation | C11: Sitewide Chat (Ask Tekton) | D11: In chat, say 'Please pray for me' and close chat before providing name or contact. | E11: Assistant prompts user for name/contact before filing request. | G11: Unknown
